Workbook

Sheet Orders
A1: Order_ID | B1: Order_Date | C1: Customer_ID | D1: Product_ID | E1: Quantity | F1: Unit_Price | G1: Discount_% | H1: Payment_Mode | I1: Region | J1: Salesperson | K1: Gross Amount | L1: Discount Amount | M1: Net Sales | N1: Sales Category | O1: Order Priority | P1: Customer_ID (Num) | Q1: Product_ID (Num) | R1: Salesperson (Cleaned) | S1: Region (Cleaned) | T1: Product Name | U1: Category | V1: Brand | W1: Supplier | X1: Product Rating
A2: ORD1001 | B2: 46037 | C2: C043 | D2: P107 | E2: 2 | F2: 2200 | G2: 0.12 | H2: Cash | I2: East | J2: Priya | K2: =PRODUCT(E2,F2) -> 4400 | L2: =PRODUCT(K2,G2) -> 528 | M2: =K2-L2 -> 3872 | N2: =IF(M2>=50000,"High Value",IF(M2>=20000,"Medium Value","Low Value")) -> Low Value | O2: =IF(AND(E2>=5,G2>=15%),"High",IF(OR(E2>=3,G2>=10%),"Medium","Low")) -> Medium | P2: =RIGHT(C2,3) -> 043 | Q2: =RIGHT(D2,3) -> 107 | R2: =PROPER(TRIM(J2)) -> Priya | S2: =TRIM(PROPER(I2)) -> East | T2: =IFERROR(VLOOKUP(D2,Product_Reference!$A$1:$F$26,2,0),"Not Found!!") -> USB-C Hub | U2: =IFERROR(VLOOKUP(D2,Product_Reference!$A$1:$F$26,3,0),"Not Found!!") -> Accessories | V2: =IFERROR(VLOOKUP(D2,Product_Reference!$A$1:$F$26,4,0),"Not Found!!") -> ConnectPro | W2: =IFERROR(VLOOKUP(D2,Product_Reference!$A$1:$F$26,5,0),"Not Found!!") -> PQR Ltd | X2: =IFERROR(VLOOKUP(D2,Product_Reference!$A$1:$F$26,6,0),"Not Found!!") -> 4.3 | AA2: 1. Calculate the total number of orders in the dataset. | AH2: 11. Create a Gross Amount column. Calculate the gross amount for every order using Quantity and Unit Price.
A3: ORD1002 | B3: 46097 | C3: C024 | D3: P119 | E3: 3 | F3: 12500 | G3: 0.08 | H3: UPI | I3: South | J3: Amit | K3: =PRODUCT(E3,F3) -> 37500 | L3: =PRODUCT(K3,G3) -> 3000 | M3: =K3-L3 -> 34500 | N3: =IF(M3>=50000,"High Value",IF(M3>=20000,"Medium Value","Low Value")) -> Medium Value | O3: =IF(AND(E3>=5,G3>=15%),"High",IF(OR(E3>=3,G3>=10%),"Medium","Low")) -> Medium | P3: =RIGHT(C3,3) -> 024 | Q3: =RIGHT(D3,3) -> 119 | R3: =PROPER(TRIM(J3)) -> Amit | S3: =TRIM(PROPER(I3)) -> South | T3: =IFERROR(VLOOKUP(D3,Product_Reference!$A$1:$F$26,2,0),"Not Found!!") -> Office Chair | U3: =IFERROR(VLOOKUP(D3,Product_Reference!$A$1:$F$26,3,0),"Not Found!!") -> Furniture | V3: =IFERROR(VLOOKUP(D3,Product_Reference!$A$1:$F$26,4,0),"Not Found!!") -> ComfortPro | W3: =IFERROR(VLOOKUP(D3,Product_Reference!$A$1:$F$26,5,0),"Not Found!!") -> ABC Ltd | X3: =IFERROR(VLOOKUP(D3,Product_Reference!$A$1:$F$26,6,0),"Not Found!!") -> 4.2 | AD3: Cash | AF3: East
A4: ORD1003 | B4: 46110 | C4: C044 | D4: P122 | E4: 2 | F4: 5500 | G4: 0.05 | H4: Net Banking | I4: West | J4: Sneha | K4: =PRODUCT(E4,F4) -> 11000 | L4: =PRODUCT(K4,G4) -> 550 | M4: =K4-L4 -> 10450 | N4: =IF(M4>=50000,"High Value",IF(M4>=20000,"Medium Value","Low Value")) -> Low Value | O4: =IF(AND(E4>=5,G4>=15%),"High",IF(OR(E4>=3,G4>=10%),"Medium","Low")) -> Low | P4: =RIGHT(C4,3) -> 044 | Q4: =RIGHT(D4,3) -> 122 | R4: =PROPER(TRIM(J4)) -> Sneha | S4: =TRIM(PROPER(I4)) -> West | T4: =IFERROR(VLOOKUP(D4,Product_Reference!$A$1:$F$26,2,0),"Not Found!!") -> Router AX1800 | U4: =IFERROR(VLOOKUP(D4,Product_Reference!$A$1:$F$26,3,0),"Not Found!!") -> Networking | V4: =IFERROR(VLOOKUP(D4,Product_Reference!$A$1:$F$26,4,0),"Not Found!!") -> NetLink | W4: =IFERROR(VLOOKUP(D4,Product_Reference!$A$1:$F$26,5,0),"Not Found!!") -> ABC Ltd | X4: =IFERROR(VLOOKUP(D4,Product_Reference!$A$1:$F$26,6,0),"Not Found!!") -> 4.5 | AA4: Total Orders | AB4: =COUNTA(A2:A151) -> 150 | AD4: UPI | AF4: South | AH4: 12. Create a Discount Amount column. Calculate the discount amount for every order.
A5: ORD1004 | B5: 46080 | C5: C022 | D5: P121 | E5: 1 | F5: 30000 | G5: 0.1 | H5: UPI | I5: East | J5: Rahul | K5: =PRODUCT(E5,F5) -> 30000 | L5: =PRODUCT(K5,G5) -> 3000 | M5: =K5-L5 -> 27000 | N5: =IF(M5>=50000,"High Value",IF(M5>=20000,"Medium Value","Low Value")) -> Medium Value | O5: =IF(AND(E5>=5,G5>=15%),"High",IF(OR(E5>=3,G5>=10%),"Medium","Low")) -> Medium | P5: =RIGHT(C5,3) -> 022 | Q5: =RIGHT(D5,3) -> 121 | R5: =PROPER(TRIM(J5)) -> Rahul | S5: =TRIM(PROPER(I5)) -> East | T5: =IFERROR(VLOOKUP(D5,Product_Reference!$A$1:$F$26,2,0),"Not Found!!") -> Portable Projector | U5: =IFERROR(VLOOKUP(D5,Product_Reference!$A$1:$F$26,3,0),"Not Found!!") -> Electronics | V5: =IFERROR(VLOOKUP(D5,Product_Reference!$A$1:$F$26,4,0),"Not Found!!") -> ViewMax | W5: =IFERROR(VLOOKUP(D5,Product_Reference!$A$1:$F$26,5,0),"Not Found!!") -> PQR Ltd | X5: =IFERROR(VLOOKUP(D5,Product_Reference!$A$1:$F$26,6,0),"Not Found!!") -> 4.1 | AD5: Net Banking | AF5: West
A6: ORD1005 | B6: 46077 | C6: C052 | D6: P110 | E6: 1 | F6: 9000 | G6: 0.1 | H6: Card | I6: North | J6: Karan | K6: =PRODUCT(E6,F6) -> 9000 | L6: =PRODUCT(K6,G6) -> 900 | M6: =K6-L6 -> 8100 | N6: =IF(M6>=50000,"High Value",IF(M6>=20000,"Medium Value","Low Value")) -> Low Value | O6: =IF(AND(E6>=5,G6>=15%),"High",IF(OR(E6>=3,G6>=10%),"Medium","Low")) -> Medium | P6: =RIGHT(C6,3) -> 052 | Q6: =RIGHT(D6,3) -> 110 | R6: =PROPER(TRIM(J6)) -> Karan | S6: =TRIM(PROPER(I6)) -> North | T6: =IFERROR(VLOOKUP(D6,Product_Reference!$A$1:$F$26,2,0),"Not Found!!") -> External SSD 1TB | U6: =IFERROR(VLOOKUP(D6,Product_Reference!$A$1:$F$26,3,0),"Not Found!!") -> Storage | V6: =IFERROR(VLOOKUP(D6,Product_Reference!$A$1:$F$26,4,0),"Not Found!!") -> DataDrive | W6: =IFERROR(VLOOKUP(D6,Product_Reference!$A$1:$F$26,5,0),"Not Found!!") -> PQR Ltd | X6: =IFERROR(VLOOKUP(D6,Product_Reference!$A$1:$F$26,6,0),"Not Found!!") -> 4.5 | AA6: 2. Calculate the total quantity of products sold. | AD6: Card | AF6: North | AH6: 13. Create a Net Sales column. Calculate the final sales value after deducting the discount.
A7: ORD1006 | B7: 46095 | C7: C039 | D7: P119 | E7: 3 | F7: 12500 | G7: 0.12 | H7: UPI | I7: East | J7: Sneha | K7: =PRODUCT(E7,F7) -> 37500 | L7: =PRODUCT(K7,G7) -> 4500 | M7: =K7-L7 -> 33000 | N7: =IF(M7>=50000,"High Value",IF(M7>=20000,"Medium Value","Low Value")) -> Medium Value | O7: =IF(AND(E7>=5,G7>=15%),"High",IF(OR(E7>=3,G7>=10%),"Medium","Low")) -> Medium | P7: =RIGHT(C7,3) -> 039 | Q7: =RIGHT(D7,3) -> 119 | R7: =PROPER(TRIM(J7)) -> Sneha | S7: =TRIM(PROPER(I7)) -> East | T7: =IFERROR(VLOOKUP(D7,Product_Reference!$A$1:$F$26,2,0),"Not Found!!") -> Office Chair | U7: =IFERROR(VLOOKUP(D7,Product_Reference!$A$1:$F$26,3,0),"Not Found!!") -> Furniture | V7: =IFERROR(VLOOKUP(D7,Product_Reference!$A$1:$F$26,4,0),"Not Found!!") -> ComfortPro | W7: =IFERROR(VLOOKUP(D7,Product_Reference!$A$1:$F$26,5,0),"Not Found!!") -> ABC Ltd | X7: =IFERROR(VLOOKUP(D7,Product_Reference!$A$1:$F$26,6,0),"Not Found!!") -> 4.2
A8: ORD1007 | B8: 46031 | C8: C026 | D8: P114 | E8: 1 | F8: 2500 | G8: 0.05 | H8: UPI | I8: South | J8: Sneha | K8: =PRODUCT(E8,F8) -> 2500 | L8: =PRODUCT(K8,G8) -> 125 | M8: =K8-L8 -> 2375 | N8: =IF(M8>=50000,"High Value",IF(M8>=20000,"Medium Value","Low Value")) -> Low Value | O8: =IF(AND(E8>=5,G8>=15%),"High",IF(OR(E8>=3,G8>=10%),"Medium","Low")) -> Low | P8: =RIGHT(C8,3) -> 026 | Q8: =RIGHT(D8,3) -> 114 | R8: =PROPER(TRIM(J8)) -> Sneha | S8: =TRIM(PROPER(I8)) -> South | T8: =IFERROR(VLOOKUP(D8,Product_Reference!$A$1:$F$26,2,0),"Not Found!!") -> Power Bank 20000mAh | U8: =IFERROR(VLOOKUP(D8,Product_Reference!$A$1:$F$26,3,0),"Not Found!!") -> Accessories | V8: =IFERROR(VLOOKUP(D8,Product_Reference!$A$1:$F$26,4,0),"Not Found!!") -> PowerPlus | W8: =IFERROR(VLOOKUP(D8,Product_Reference!$A$1:$F$26,5,0),"Not Found!!") -> PQR Ltd | X8: =IFERROR(VLOOKUP(D8,Product_Reference!$A$1:$F$26,6,0),"Not Found!!") -> 4.1 | AA8: Total Qty Sold | AB8: =SUM(E2:E151) -> 408 | AF8: Priya | AH8: 14. Create a Sales Category column. Classify each order as High Value, Medium Value, or Low Value based on Net Sales: High Value = ₹50,000 or more; Medium Value = ₹20,000 or more but below ₹50,000; Low Value = below ₹20,000.
A9: ORD1008 | B9: 46030 | C9: C047 | D9: P115 | E9: 3 | F9: 42000 | G9: 0.1 | H9: UPI | I9: East | J9: Sneha | K9: =PRODUCT(E9,F9) -> 126000 | L9: =PRODUCT(K9,G9) -> 12600 | M9: =K9-L9 -> 113400 | N9: =IF(M9>=50000,"High Value",IF(M9>=20000,"Medium Value","Low Value")) -> High Value | O9: =IF(AND(E9>=5,G9>=15%),"High",IF(OR(E9>=3,G9>=10%),"Medium","Low")) -> Medium | P9: =RIGHT(C9,3) -> 047 | Q9: =RIGHT(D9,3) -> 115 | R9: =PROPER(TRIM(J9)) -> Sneha | S9: =TRIM(PROPER(I9)) -> East | T9: =IFERROR(VLOOKUP(D9,Product_Reference!$A$1:$F$26,2,0),"Not Found!!") -> Smart TV 43 | U9: =IFERROR(VLOOKUP(D9,Product_Reference!$A$1:$F$26,3,0),"Not Found!!") -> Electronics | V9: =IFERROR(VLOOKUP(D9,Product_Reference!$A$1:$F$26,4,0),"Not Found!!") -> ViewMax | W9: =IFERROR(VLOOKUP(D9,Product_Reference!$A$1:$F$26,5,0),"Not Found!!") -> ABC Ltd | X9: =IFERROR(VLOOKUP(D9,Product_Reference!$A$1:$F$26,6,0),"Not Found!!") -> 4.6 | AF9: Amit
A10: ORD1009 | B10: 46024 | C10: C006 | D10: P118 | E10: 4 | F10: 650 | H10: UPI | I10: South | J10: Neha | K10: =PRODUCT(E10,F10) -> 2600 | L10: =PRODUCT(K10,G10) -> 2600 | M10: =K10-L10 -> 0 | N10: =IF(M10>=50000,"High Value",IF(M10>=20000,"Medium Value","Low Value")) -> Low Value | O10: =IF(AND(E10>=5,G10>=15%),"High",IF(OR(E10>=3,G10>=10%),"Medium","Low")) -> Medium | P10: =RIGHT(C10,3) -> 006 | Q10: =RIGHT(D10,3) -> 118 | R10: =PROPER(TRIM(J10)) -> Neha | S10: =TRIM(PROPER(I10)) -> South | T10: =IFERROR(VLOOKUP(D10,Product_Reference!$A$1:$F$26,2,0),"Not Found!!") -> Mechanical Pencil Set | U10: =IFERROR(VLOOKUP(D10,Product_Reference!$A$1:$F$26,3,0),"Not Found!!") -> Stationery | V10: =IFERROR(VLOOKUP(D10,Product_Reference!$A$1:$F$26,4,0),"Not Found!!") -> WriteWell | W10: =IFERROR(VLOOKUP(D10,Product_Reference!$A$1:$F$26,5,0),"Not Found!!") -> LMN Ltd | X10: =IFERROR(VLOOKUP(D10,Product_Reference!$A$1:$F$26,6,0),"Not Found!!") -> 4.3 | AA10: 3. Calculate the average quantity ordered per order. | AF10: Sneha | AH10: 15. Create an Order Priority column. Classify an order as High when Quantity is at least 5 AND Discount is at least 15%; Medium when Quantity is at least 3 OR Discount is at least 10%; otherwise classify it as Low.
A11: ORD1010 | B11: 46056 | C11: C010 | D11: P118 | E11: 6 | F11: 650 | G11: 0.1 | H11: Net Banking | I11: West | J11: Neha | K11: =PRODUCT(E11,F11) -> 3900 | L11: =PRODUCT(K11,G11) -> 390 | M11: =K11-L11 -> 3510 | N11: =IF(M11>=50000,"High Value",IF(M11>=20000,"Medium Value","Low Value")) -> Low Value | O11: =IF(AND(E11>=5,G11>=15%),"High",IF(OR(E11>=3,G11>=10%),"Medium","Low")) -> Medium | P11: =RIGHT(C11,3) -> 010 | Q11: =RIGHT(D11,3) -> 118 | R11: =PROPER(TRIM(J11)) -> Neha | S11: =TRIM(PROPER(I11)) -> West | T11: =IFERROR(VLOOKUP(D11,Product_Reference!$A$1:$F$26,2,0),"Not Found!!") -> Mechanical Pencil Set | U11: =IFERROR(VLOOKUP(D11,Product_Reference!$A$1:$F$26,3,0),"Not Found!!") -> Stationery | V11: =IFERROR(VLOOKUP(D11,Product_Reference!$A$1:$F$26,4,0),"Not Found!!") -> WriteWell | W11: =IFERROR(VLOOKUP(D11,Product_Reference!$A$1:$F$26,5,0),"Not Found!!") -> LMN Ltd | X11: =IFERROR(VLOOKUP(D11,Product_Reference!$A$1:$F$26,6,0),"Not Found!!") -> 4.3 | AF11: Rahul
A12: ORD1011 | B12: 46062 | C12: C021 | D12: P123 | E12: 5 | F12: 2800 | G12: 0.15 | H12: UPI | I12: West | J12: Karan | K12: =PRODUCT(E12,F12) -> 14000 | L12: =PRODUCT(K12,G12) -> 2100 | M12: =K12-L12 -> 11900 | N12: =IF(M12>=50000,"High Value",IF(M12>=20000,"Medium Value","Low Value")) -> Low Value | O12: =IF(AND(E12>=5,G12>=15%),"High",IF(OR(E12>=3,G12>=10%),"Medium","Low")) -> High | P12: =RIGHT(C12,3) -> 021 | Q12: =RIGHT(D12,3) -> 123 | R12: =PROPER(TRIM(J12)) -> Karan | S12: =TRIM(PROPER(I12)) -> West | T12: =IFERROR(VLOOKUP(D12,Product_Reference!$A$1:$F$26,2,0),"Not Found!!") -> Wi-Fi Range Extender | U12: =IFERROR(VLOOKUP(D12,Product_Reference!$A$1:$F$26,3,0),"Not Found!!") -> Networking | V12: =IFERROR(VLOOKUP(D12,Product_Reference!$A$1:$F$26,4,0),"Not Found!!") -> NetLink | W12: =IFERROR(VLOOKUP(D12,Product_Reference!$A$1:$F$26,5,0),"Not Found!!") -> XYZ Ltd | X12: =IFERROR(VLOOKUP(D12,Product_Reference!$A$1:$F$26,6,0),"Not Found!!") -> 4 | AA12: Average Qty Ordered | AB12: =AVERAGE(E2:E53) -> 2.6730769 | AF12: Karan | AH12: 16. Create a new column containing only the numeric portion of Customer_ID. For example, C001 should return 001.
A13: ORD1012 | B13: 46082 | C13: C060 | D13: P124 | E13: 6 | F13: 2500 | G13: 0 | H13: UPI | I13: East | J13: Karan | K13: =PRODUCT(E13,F13) -> 15000 | L13: =PRODUCT(K13,G13) -> 0 | M13: =K13-L13 -> 15000 | N13: =IF(M13>=50000,"High Value",IF(M13>=20000,"Medium Value","Low Value")) -> Low Value | O13: =IF(AND(E13>=5,G13>=15%),"High",IF(OR(E13>=3,G13>=10%),"Medium","Low")) -> Medium | P13: =RIGHT(C13,3) -> 060 | Q13: =RIGHT(D13,3) -> 124 | R13: =PROPER(TRIM(J13)) -> Karan | S13: =TRIM(PROPER(I13)) -> East | T13: =IFERROR(VLOOKUP(D13,Product_Reference!$A$1:$F$26,2,0),"Not Found!!") -> Tablet Keyboard | U13: =IFERROR(VLOOKUP(D13,Product_Reference!$A$1:$F$26,3,0),"Not Found!!") -> Accessories | V13: =IFERROR(VLOOKUP(D13,Product_Reference!$A$1:$F$26,4,0),"Not Found!!") -> KeyMaster | W13: =IFERROR(VLOOKUP(D13,Product_Reference!$A$1:$F$26,5,0),"Not Found!!") -> PQR Ltd | X13: =IFERROR(VLOOKUP(D13,Product_Reference!$A$1:$F$26,6,0),"Not Found!!") -> 3.8 | AF13: Neha
A14: ORD1013 | B14: 46031 | C14: C024 | D14: P101 | E14: 5 | F14: 45000 | G14: 0.18 | H14: UPI | I14: east | J14: Amit | K14: =PRODUCT(E14,F14) -> 225000 | L14: =PRODUCT(K14,G14) -> 40500 | M14: =K14-L14 -> 184500 | N14: =IF(M14>=50000,"High Value",IF(M14>=20000,"Medium Value","Low Value")) -> High Value | O14: =IF(AND(E14>=5,G14>=15%),"High",IF(OR(E14>=3,G14>=10%),"Medium","Low")) -> High | P14: =RIGHT(C14,3) -> 024 | Q14: =RIGHT(D14,3) -> 101 | R14: =PROPER(TRIM(J14)) -> Amit | S14: =TRIM(PROPER(I14)) -> East | T14: =IFERROR(VLOOKUP(D14,Product_Reference!$A$1:$F$26,2,0),"Not Found!!") -> Laptop Pro 14 | U14: =IFERROR(VLOOKUP(D14,Product_Reference!$A$1:$F$26,3,0),"Not Found!!") -> Electronics | V14: =IFERROR(VLOOKUP(D14,Product_Reference!$A$1:$F$26,4,0),"Not Found!!") -> TechPro | W14: =IFERROR(VLOOKUP(D14,Product_Reference!$A$1:$F$26,5,0),"Not Found!!") -> ABC Ltd | X14: =IFERROR(VLOOKUP(D14,Product_Reference!$A$1:$F$26,6,0),"Not Found!!") -> 4.5 | AA14: 4. Find the number of orders made using each payment mode: UPI, Card, Cash, and Net Banking.
A15: ORD1014 | B15: 46057 | C15: C035 | D15: P119 | E15: 1 | F15: 12500 | G15: 0.2 | H15: Cash | I15: East | J15: Priya | K15: =PRODUCT(E15,F15) -> 12500 | L15: =PRODUCT(K15,G15) -> 2500 | M15: =K15-L15 -> 10000 | N15: =IF(M15>=50000,"High Value",IF(M15>=20000,"Medium Value","Low Value")) -> Low Value | O15: =IF(AND(E15>=5,G15>=15%),"High",IF(OR(E15>=3,G15>=10%),"Medium","Low")) -> Medium | P15: =RIGHT(C15,3) -> 035 | Q15: =RIGHT(D15,3) -> 119 | R15: =PROPER(TRIM(J15)) -> Priya | S15: =TRIM(PROPER(I15)) -> East | T15: =IFERROR(VLOOKUP(D15,Product_Reference!$A$1:$F$26,2,0),"Not Found!!") -> Office Chair | U15: =IFERROR(VLOOKUP(D15,Product_Reference!$A$1:$F$26,3,0),"Not Found!!") -> Furniture | V15: =IFERROR(VLOOKUP(D15,Product_Reference!$A$1:$F$26,4,0),"Not Found!!") -> ComfortPro | W15: =IFERROR(VLOOKUP(D15,Product_Reference!$A$1:$F$26,5,0),"Not Found!!") -> ABC Ltd | X15: =IFERROR(VLOOKUP(D15,Product_Reference!$A$1:$F$26,6,0),"Not Found!!") -> 4.2 | AH15: 17. Create a new column containing only the numeric portion of Product_ID. For example, P101 should return 101.
A16: ORD1015 | B16: 46050 | C16: C007 | D16: P107 | E16: 6 | F16: 2200 | G16: 0 | H16: Net Banking | I16: South | J16: Priya | K16: =PRODUCT(E16,F16) -> 13200 | L16: =PRODUCT(K16,G16) -> 0 | M16: =K16-L16 -> 13200 | N16: =IF(M16>=50000,"High Value",IF(M16>=20000,"Medium Value","Low Value")) -> Low Value | O16: =IF(AND(E16>=5,G16>=15%),"High",IF(OR(E16>=3,G16>=10%),"Medium","Low")) -> Medium | P16: =RIGHT(C16,3) -> 007 | Q16: =RIGHT(D16,3) -> 107 | R16: =PROPER(TRIM(J16)) -> Priya | S16: =TRIM(PROPER(I16)) -> South | T16: =IFERROR(VLOOKUP(D16,Product_Reference!$A$1:$F$26,2,0),"Not Found!!") -> USB-C Hub | U16: =IFERROR(VLOOKUP(D16,Product_Reference!$A$1:$F$26,3,0),"Not Found!!") -> Accessories | V16: =IFERROR(VLOOKUP(D16,Product_Reference!$A$1:$F$26,4,0),"Not Found!!") -> ConnectPro | W16: =IFERROR(VLOOKUP(D16,Product_Reference!$A$1:$F$26,5,0),"Not Found!!") -> PQR Ltd | X16: =IFERROR(VLOOKUP(D16,Product_Reference!$A$1:$F$26,6,0),"Not Found!!") -> 4.3 | AA16: Payment_Mode | AB16: No.of Orders
A17: ORD1016 | B17: 46084 | C17: C024 | D17: P101 | E17: 3 | F17: 45000 | G17: 0.18 | H17: Card | I17: South | J17: Neha | K17: =PRODUCT(E17,F17) -> 135000 | L17: =PRODUCT(K17,G17) -> 24300 | M17: =K17-L17 -> 110700 | N17: =IF(M17>=50000,"High Value",IF(M17>=20000,"Medium Value","Low Value")) -> High Value | O17: =IF(AND(E17>=5,G17>=15%),"High",IF(OR(E17>=3,G17>=10%),"Medium","Low")) -> Medium | P17: =RIGHT(C17,3) -> 024 | Q17: =RIGHT(D17,3) -> 101 | R17: =PROPER(TRIM(J17)) -> Neha | S17: =TRIM(PROPER(I17)) -> South | T17: =IFERROR(VLOOKUP(D17,Product_Reference!$A$1:$F$26,2,0),"Not Found!!") -> Laptop Pro 14 | U17: =IFERROR(VLOOKUP(D17,Product_Reference!$A$1:$F$26,3,0),"Not Found!!") -> Electronics | V17: =IFERROR(VLOOKUP(D17,Product_Reference!$A$1:$F$26,4,0),"Not Found!!") -> TechPro | W17: =IFERROR(VLOOKUP(D17,Product_Reference!$A$1:$F$26,5,0),"Not Found!!") -> ABC Ltd | X17: =IFERROR(VLOOKUP(D17,Product_Reference!$A$1:$F$26,6,0),"Not Found!!") -> 4.5 | AA17: Cash | AB17: =COUNTIF(H2:H92,AA17) -> 6 | AH17: 18. Create a cleaned Salesperson column in Proper Case.
A18: ORD1017 | B18: 46069 | C18: C014 | D18: P103 | E18: 1 | F18: 65000 | G18: 0.08 | H18: Net Banking | I18: East | J18: Priya | K18: =PRODUCT(E18,F18) -> 65000 | L18: =PRODUCT(K18,G18) -> 5200 | M18: =K18-L18 -> 59800 | N18: =IF(M18>=50000,"High Value",IF(M18>=20000,"Medium Value","Low Value")) -> High Value | O18: =IF(AND(E18>=5,G18>=15%),"High",IF(OR(E18>=3,G18>=10%),"Medium","Low")) -> Low | P18: =RIGHT(C18,3) -> 014 | Q18: =RIGHT(D18,3) -> 103 | R18: =PROPER(TRIM(J18)) -> Priya | S18: =TRIM(PROPER(I18)) -> East | T18: =IFERROR(VLOOKUP(D18,Product_Reference!$A$1:$F$26,2,0),"Not Found!!") -> Smartphone X | U18: =IFERROR(VLOOKUP(D18,Product_Reference!$A$1:$F$26,3,0),"Not Found!!") -> Electronics | V18: =IFERROR(VLOOKUP(D18,Product_Reference!$A$1:$F$26,4,0),"Not Found!!") -> MobileMax | W18: =IFERROR(VLOOKUP(D18,Product_Reference!$A$1:$F$26,5,0),"Not Found!!") -> ABC Ltd | X18: =IFERROR(VLOOKUP(D18,Product_Reference!$A$1:$F$26,6,0),"Not Found!!") -> 4.6
A19: ORD1018 | B19: 46031 | C19: C015 | D19: P123 | E19: 3 | F19: 2800 | G19: 0.08 | H19: Card | I19: West | J19: Sneha | K19: =PRODUCT(E19,F19) -> 8400 | L19: =PRODUCT(K19,G19) -> 672 | M19: =K19-L19 -> 7728 | N19: =IF(M19>=50000,"High Value",IF(M19>=20000,"Medium Value","Low Value")) -> Low Value | O19: =IF(AND(E19>=5,G19>=15%),"High",IF(OR(E19>=3,G19>=10%),"Medium","Low")) -> Medium | P19: =RIGHT(C19,3) -> 015 | Q19: =RIGHT(D19,3) -> 123 | R19: =PROPER(TRIM(J19)) -> Sneha | S19: =TRIM(PROPER(I19)) -> West | T19: =IFERROR(VLOOKUP(D19,Product_Reference!$A$1:$F$26,2,0),"Not Found!!") -> Wi-Fi Range Extender | U19: =IFERROR(VLOOKUP(D19,Product_Reference!$A$1:$F$26,3,0),"Not Found!!") -> Networking | V19: =IFERROR(VLOOKUP(D19,Product_Reference!$A$1:$F$26,4,0),"Not Found!!") -> NetLink | W19: =IFERROR(VLOOKUP(D19,Product_Reference!$A$1:$F$26,5,0),"Not Found!!") -> XYZ Ltd | X19: =IFERROR(VLOOKUP(D19,Product_Reference!$A$1:$F$26,6,0),"Not Found!!") -> 4 | AA19: 5. Find the number of orders received from each region: East, West, North, and South. | AH19: 19. Create a cleaned Region column by removing unnecessary leading and trailing spaces.
A20: ORD1019 | B20: 46074 | C20: C032 | D20: P113 | E20: 1 | F20: 5500 | G20: 0.18 | H20: Card | I20: East | J20: Karan | K20: =PRODUCT(E20,F20) -> 5500 | L20: =PRODUCT(K20,G20) -> 990 | M20: =K20-L20 -> 4510 | N20: =IF(M20>=50000,"High Value",IF(M20>=20000,"Medium Value","Low Value")) -> Low Value | O20: =IF(AND(E20>=5,G20>=15%),"High",IF(OR(E20>=3,G20>=10%),"Medium","Low")) -> Medium | P20: =RIGHT(C20,3) -> 032 | Q20: =RIGHT(D20,3) -> 113 | R20: =PROPER(TRIM(J20)) -> Karan | S20: =TRIM(PROPER(I20)) -> East | T20: =IFERROR(VLOOKUP(D20,Product_Reference!$A$1:$F$26,2,0),"Not Found!!") -> Wireless Earbuds | U20: =IFERROR(VLOOKUP(D20,Product_Reference!$A$1:$F$26,3,0),"Not Found!!") -> Audio | V20: =IFERROR(VLOOKUP(D20,Product_Reference!$A$1:$F$26,4,0),"Not Found!!") -> SoundMax | W20: =IFERROR(VLOOKUP(D20,Product_Reference!$A$1:$F$26,5,0),"Not Found!!") -> LMN Ltd | X20: =IFERROR(VLOOKUP(D20,Product_Reference!$A$1:$F$26,6,0),"Not Found!!") -> 4.4
A21: ORD1020 | B21: 46054 | C21: C007 | D21: P115 | E21: 2 | F21: 42000 | G21: 0.12 | H21: UPI | I21: West | J21: Sneha | K21: =PRODUCT(E21,F21) -> 84000 | L21: =PRODUCT(K21,G21) -> 10080 | M21: =K21-L21 -> 73920 | N21: =IF(M21>=50000,"High Value",IF(M21>=20000,"Medium Value","Low Value")) -> High Value | O21: =IF(AND(E21>=5,G21>=15%),"High",IF(OR(E21>=3,G21>=10%),"Medium","Low")) -> Medium | P21: =RIGHT(C21,3) -> 007 | Q21: =RIGHT(D21,3) -> 115 | R21: =PROPER(TRIM(J21)) -> Sneha | S21: =TRIM(PROPER(I21)) -> West | T21: =IFERROR(VLOOKUP(D21,Product_Reference!$A$1:$F$26,2,0),"Not Found!!") -> Smart TV 43 | U21: =IFERROR(VLOOKUP(D21,Product_Reference!$A$1:$F$26,3,0),"Not Found!!") -> Electronics | V21: =IFERROR(VLOOKUP(D21,Product_Reference!$A$1:$F$26,4,0),"Not Found!!") -> ViewMax | W21: =IFERROR(VLOOKUP(D21,Product_Reference!$A$1:$F$26,5,0),"Not Found!!") -> ABC Ltd | X21: =IFERROR(VLOOKUP(D21,Product_Reference!$A$1:$F$26,6,0),"Not Found!!") -> 4.6 | AA21: Region | AB21: No. of Orders | AH21: 20. Using VLOOKUP, retrieve the Product Name for every order.
A22: ORD1021 | B22: 46084 | C22: C057 | D22: P102 | E22: 6 | F22: 1200 | G22: 0.12 | H22: UPI | I22: South | J22: Sneha | K22: =PRODUCT(E22,F22) -> 7200 | L22: =PRODUCT(K22,G22) -> 864 | M22: =K22-L22 -> 6336 | N22: =IF(M22>=50000,"High Value",IF(M22>=20000,"Medium Value","Low Value")) -> Low Value | O22: =IF(AND(E22>=5,G22>=15%),"High",IF(OR(E22>=3,G22>=10%),"Medium","Low")) -> Medium | P22: =RIGHT(C22,3) -> 057 | Q22: =RIGHT(D22,3) -> 102 | R22: =PROPER(TRIM(J22)) -> Sneha | S22: =TRIM(PROPER(I22)) -> South | T22: =IFERROR(VLOOKUP(D22,Product_Reference!$A$1:$F$26,2,0),"Not Found!!") -> Wireless Mouse | U22: =IFERROR(VLOOKUP(D22,Product_Reference!$A$1:$F$26,3,0),"Not Found!!") -> Accessories | V22: =IFERROR(VLOOKUP(D22,Product_Reference!$A$1:$F$26,4,0),"Not Found!!") -> ClickTech | W22: =IFERROR(VLOOKUP(D22,Product_Reference!$A$1:$F$26,5,0),"Not Found!!") -> XYZ Ltd | X22: =IFERROR(VLOOKUP(D22,Product_Reference!$A$1:$F$26,6,0),"Not Found!!") -> 4.2 | AA22: East | AB22: =COUNTIF(S2:S151,AA22) -> 33
A23: ORD1022 | B23: 46084 | C23: C011 | D23: P112 | E23: 2 | F23: 3200 | G23: 0.15 | H23: UPI | I23: North | J23: Sneha | K23: =PRODUCT(E23,F23) -> 6400 | L23: =PRODUCT(K23,G23) -> 960 | M23: =K23-L23 -> 5440 | N23: =IF(M23>=50000,"High Value",IF(M23>=20000,"Medium Value","Low Value")) -> Low Value | O23: =IF(AND(E23>=5,G23>=15%),"High",IF(OR(E23>=3,G23>=10%),"Medium","Low")) -> Medium | P23: =RIGHT(C23,3) -> 011 | Q23: =RIGHT(D23,3) -> 112 | R23: =PROPER(TRIM(J23)) -> Sneha | S23: =TRIM(PROPER(I23)) -> North | T23: =IFERROR(VLOOKUP(D23,Product_Reference!$A$1:$F$26,2,0),"Not Found!!") -> Webcam HD | U23: =IFERROR(VLOOKUP(D23,Product_Reference!$A$1:$F$26,3,0),"Not Found!!") -> Accessories | V23: =IFERROR(VLOOKUP(D23,Product_Reference!$A$1:$F$26,4,0),"Not Found!!") -> VisionTech | W23: =IFERROR(VLOOKUP(D23,Product_Reference!$A$1:$F$26,5,0),"Not Found!!") -> ABC Ltd | X23: =IFERROR(VLOOKUP(D23,Product_Reference!$A$1:$F$26,6,0),"Not Found!!") -> 3.8 | AH23: 21. Using VLOOKUP, retrieve the Category for every order.
A24: ORD1023 | B24: 46023 | C24: C057 | D24: P125 | E24: 3 | F24: 16000 | G24: 0.15 | H24: Card | J24: Sneha | K24: =PRODUCT(E24,F24) -> 48000 | L24: =PRODUCT(K24,G24) -> 7200 | M24: =K24-L24 -> 40800 | N24: =IF(M24>=50000,"High Value",IF(M24>=20000,"Medium Value","Low Value")) -> Medium Value | O24: =IF(AND(E24>=5,G24>=15%),"High",IF(OR(E24>=3,G24>=10%),"Medium","Low")) -> Medium | P24: =RIGHT(C24,3) -> 057 | Q24: =RIGHT(D24,3) -> 125 | R24: =PROPER(TRIM(J24)) -> Sneha | S24: =TRIM(PROPER(I24)) | T24: =IFERROR(VLOOKUP(D24,Product_Reference!$A$1:$F$26,2,0),"Not Found!!") -> Laser Printer | U24: =IFERROR(VLOOKUP(D24,Product_Reference!$A$1:$F$26,3,0),"Not Found!!") -> Office Equipment | V24: =IFERROR(VLOOKUP(D24,Product_Reference!$A$1:$F$26,4,0),"Not Found!!") -> PrintPro | W24: =IFERROR(VLOOKUP(D24,Product_Reference!$A$1:$F$26,5,0),"Not Found!!") -> ABC Ltd | X24: =IFERROR(VLOOKUP(D24,Product_Reference!$A$1:$F$26,6,0),"Not Found!!") -> 4.2 | AA24: 6. Find the number of orders where Quantity is greater than or equal to 3.
A25: ORD1024 | B25: 46092 | C25: C008 | D25: P113 | E25: 5 | F25: 5500 | G25: 0.08 | H25: Card | I25: West | J25: Karan | K25: =PRODUCT(E25,F25) -> 27500 | L25: =PRODUCT(K25,G25) -> 2200 | M25: =K25-L25 -> 25300 | N25: =IF(M25>=50000,"High Value",IF(M25>=20000,"Medium Value","Low Value")) -> Medium Value | O25: =IF(AND(E25>=5,G25>=15%),"High",IF(OR(E25>=3,G25>=10%),"Medium","Low")) -> Medium | P25: =RIGHT(C25,3) -> 008 | Q25: =RIGHT(D25,3) -> 113 | R25: =PROPER(TRIM(J25)) -> Karan | S25: =TRIM(PROPER(I25)) -> West | T25: =IFERROR(VLOOKUP(D25,Product_Reference!$A$1:$F$26,2,0),"Not Found!!") -> Wireless Earbuds | U25: =IFERROR(VLOOKUP(D25,Product_Reference!$A$1:$F$26,3,0),"Not Found!!") -> Audio | V25: =IFERROR(VLOOKUP(D25,Product_Reference!$A$1:$F$26,4,0),"Not Found!!") -> SoundMax | W25: =IFERROR(VLOOKUP(D25,Product_Reference!$A$1:$F$26,5,0),"Not Found!!") -> LMN Ltd | X25: =IFERROR(VLOOKUP(D25,Product_Reference!$A$1:$F$26,6,0),"Not Found!!") -> 4.4 | AH25: 22. Using VLOOKUP, retrieve the Brand for every order.
A26: ORD1025 | B26: 46066 | C26: C024 | D26: P101 | E26: 1 | F26: 45000 | G26: 0.05 | H26: Net Banking | I26: West | J26: Rahul | K26: =PRODUCT(E26,F26) -> 45000 | L26: =PRODUCT(K26,G26) -> 2250 | M26: =K26-L26 -> 42750 | N26: =IF(M26>=50000,"High Value",IF(M26>=20000,"Medium Value","Low Value")) -> Medium Value | O26: =IF(AND(E26>=5,G26>=15%),"High",IF(OR(E26>=3,G26>=10%),"Medium","Low")) -> Low | P26: =RIGHT(C26,3) -> 024 | Q26: =RIGHT(D26,3) -> 101 | R26: =PROPER(TRIM(J26)) -> Rahul | S26: =TRIM(PROPER(I26)) -> West | T26: =IFERROR(VLOOKUP(D26,Product_Reference!$A$1:$F$26,2,0),"Not Found!!") -> Laptop Pro 14 | U26: =IFERROR(VLOOKUP(D26,Product_Reference!$A$1:$F$26,3,0),"Not Found!!") -> Electronics | V26: =IFERROR(VLOOKUP(D26,Product_Reference!$A$1:$F$26,4,0),"Not Found!!") -> TechPro | W26: =IFERROR(VLOOKUP(D26,Product_Reference!$A$1:$F$26,5,0),"Not Found!!") -> ABC Ltd | X26: =IFERROR(VLOOKUP(D26,Product_Reference!$A$1:$F$26,6,0),"Not Found!!") -> 4.5 | AA26: No. of Orders gte 3 | AB26: =COUNTIF(E2:E151,">=3") -> 64
A27: ORD1026 | B27: 46080 | C27: C052 | D27: P120 | E27: 1 | F27: 2200 | G27: 0.15 | H27: UPI | I27: North | J27: Priya | K27: =PRODUCT(E27,F27) -> 2200 | L27: =PRODUCT(K27,G27) -> 330 | M27: =K27-L27 -> 1870 | N27: =IF(M27>=50000,"High Value",IF(M27>=20000,"Medium Value","Low Value")) -> Low Value | O27: =IF(AND(E27>=5,G27>=15%),"High",IF(OR(E27>=3,G27>=10%),"Medium","Low")) -> Medium | P27: =RIGHT(C27,3) -> 052 | Q27: =RIGHT(D27,3) -> 120 | R27: =PROPER(TRIM(J27)) -> Priya | S27: =TRIM(PROPER(I27)) -> North | T27: =IFERROR(VLOOKUP(D27,Product_Reference!$A$1:$F$26,2,0),"Not Found!!") -> Desk Lamp | U27: =IFERROR(VLOOKUP(D27,Product_Reference!$A$1:$F$26,3,0),"Not Found!!") -> Furniture | V27: =IFERROR(VLOOKUP(D27,Product_Reference!$A$1:$F$26,4,0),"Not Found!!") -> BrightHome | W27: =IFERROR(VLOOKUP(D27,Product_Reference!$A$1:$F$26,5,0),"Not Found!!") -> XYZ Ltd | X27: =IFERROR(VLOOKUP(D27,Product_Reference!$A$1:$F$26,6,0),"Not Found!!") -> 3.9 | AH27: 23. Using VLOOKUP, retrieve the Supplier for every order.
A28: ORD1027 | B28: 46078 | C28: C017 | D28: P103 | E28: 1 | F28: 65000 | G28: 0.12 | H28: UPI | I28: West | J28: Priya | K28: =PRODUCT(E28,F28) -> 65000 | L28: =PRODUCT(K28,G28) -> 7800 | M28: =K28-L28 -> 57200 | N28: =IF(M28>=50000,"High Value",IF(M28>=20000,"Medium Value","Low Value")) -> High Value | O28: =IF(AND(E28>=5,G28>=15%),"High",IF(OR(E28>=3,G28>=10%),"Medium","Low")) -> Medium | P28: =RIGHT(C28,3) -> 017 | Q28: =RIGHT(D28,3) -> 103 | R28: =PROPER(TRIM(J28)) -> Priya | S28: =TRIM(PROPER(I28)) -> West | T28: =IFERROR(VLOOKUP(D28,Product_Reference!$A$1:$F$26,2,0),"Not Found!!") -> Smartphone X | U28: =IFERROR(VLOOKUP(D28,Product_Reference!$A$1:$F$26,3,0),"Not Found!!") -> Electronics | V28: =IFERROR(VLOOKUP(D28,Product_Reference!$A$1:$F$26,4,0),"Not Found!!") -> MobileMax | W28: =IFERROR(VLOOKUP(D28,Product_Reference!$A$1:$F$26,5,0),"Not Found!!") -> ABC Ltd | X28: =IFERROR(VLOOKUP(D28,Product_Reference!$A$1:$F$26,6,0),"Not Found!!") -> 4.6 | AA28: 7. Find the number of orders where Discount is greater than 10%.
A29: ORD1028 | B29: 46023 | C29: C019 | D29: P122 | E29: 3 | F29: 5500 | G29: 0.12 | H29: Card | I29: East | J29: Sneha | K29: =PRODUCT(E29,F29) -> 16500 | L29: =PRODUCT(K29,G29) -> 1980 | M29: =K29-L29 -> 14520 | N29: =IF(M29>=50000,"High Value",IF(M29>=20000,"Medium Value","Low Value")) -> Low Value | O29: =IF(AND(E29>=5,G29>=15%),"High",IF(OR(E29>=3,G29>=10%),"Medium","Low")) -> Medium | P29: =RIGHT(C29,3) -> 019 | Q29: =RIGHT(D29,3) -> 122 | R29: =PROPER(TRIM(J29)) -> Sneha | S29: =TRIM(PROPER(I29)) -> East | T29: =IFERROR(VLOOKUP(D29,Product_Reference!$A$1:$F$26,2,0),"Not Found!!") -> Router AX1800 | U29: =IFERROR(VLOOKUP(D29,Product_Reference!$A$1:$F$26,3,0),"Not Found!!") -> Networking | V29: =IFERROR(VLOOKUP(D29,Product_Reference!$A$1:$F$26,4,0),"Not Found!!") -> NetLink | W29: =IFERROR(VLOOKUP(D29,Product_Reference!$A$1:$F$26,5,0),"Not Found!!") -> ABC Ltd | X29: =IFERROR(VLOOKUP(D29,Product_Reference!$A$1:$F$26,6,0),"Not Found!!") -> 4.5 | AH29: 24. Using VLOOKUP, retrieve the Product Rating for every order.
A30: ORD1029 | B30: 46077 | C30: C011 | D30: P106 | E30: 3 | F30: 4500 | G30: 0.1 | H30: UPI | I30: WEST | J30: Neha | K30: =PRODUCT(E30,F30) -> 13500 | L30: =PRODUCT(K30,G30) -> 1350 | M30: =K30-L30 -> 12150 | N30: =IF(M30>=50000,"High Value",IF(M30>=20000,"Medium Value","Low Value")) -> Low Value | O30: =IF(AND(E30>=5,G30>=15%),"High",IF(OR(E30>=3,G30>=10%),"Medium","Low")) -> Medium | P30: =RIGHT(C30,3) -> 011 | Q30: =RIGHT(D30,3) -> 106 | R30: =PROPER(TRIM(J30)) -> Neha | S30: =TRIM(PROPER(I30)) -> West | T30: =IFERROR(VLOOKUP(D30,Product_Reference!$A$1:$F$26,2,0),"Not Found!!") -> Bluetooth Speaker | U30: =IFERROR(VLOOKUP(D30,Product_Reference!$A$1:$F$26,3,0),"Not Found!!") -> Audio | V30: =IFERROR(VLOOKUP(D30,Product_Reference!$A$1:$F$26,4,0),"Not Found!!") -> SoundMax | W30: =IFERROR(VLOOKUP(D30,Product_Reference!$A$1:$F$26,5,0),"Not Found!!") -> LMN Ltd | X30: =IFERROR(VLOOKUP(D30,Product_Reference!$A$1:$F$26,6,0),"Not Found!!") -> 3.9 | AA30: No. orders disc > 10% | AB30: =COUNTIF(G2:G151,">10%") -> 81
A31: ORD1030 | B31: 46092 | C31: C022 | D31: P124 | E31: 2 | F31: 2500 | G31: 0.1 | H31: Card | I31: South | J31: Rahul | K31: =PRODUCT(E31,F31) -> 5000 | L31: =PRODUCT(K31,G31) -> 500 | M31: =K31-L31 -> 4500 | N31: =IF(M31>=50000,"High Value",IF(M31>=20000,"Medium Value","Low Value")) -> Low Value | O31: =IF(AND(E31>=5,G31>=15%),"High",IF(OR(E31>=3,G31>=10%),"Medium","Low")) -> Medium | P31: =RIGHT(C31,3) -> 022 | Q31: =RIGHT(D31,3) -> 124 | R31: =PROPER(TRIM(J31)) -> Rahul | S31: =TRIM(PROPER(I31)) -> South | T31: =IFERROR(VLOOKUP(D31,Product_Reference!$A$1:$F$26,2,0),"Not Found!!") -> Tablet Keyboard | U31: =IFERROR(VLOOKUP(D31,Product_Reference!$A$1:$F$26,3,0),"Not Found!!") -> Accessories | V31: =IFERROR(VLOOKUP(D31,Product_Reference!$A$1:$F$26,4,0),"Not Found!!") -> KeyMaster | W31: =IFERROR(VLOOKUP(D31,Product_Reference!$A$1:$F$26,5,0),"Not Found!!") -> PQR Ltd | X31: =IFERROR(VLOOKUP(D31,Product_Reference!$A$1:$F$26,6,0),"Not Found!!") -> 3.8 | AH31: 25. Retrieve Product Name, Category, Brand, Supplier, and Product Rating using the multi-value VLOOKUP technique covered in class.
A32: ORD1031 | B32: 46025 | C32: C020 | D32: P109 | E32: 3 | F32: 8500 | G32: 0.2 | H32: UPI | I32: South | J32: Amit | K32: =PRODUCT(E32,F32) -> 25500 | L32: =PRODUCT(K32,G32) -> 5100 | M32: =K32-L32 -> 20400 | N32: =IF(M32>=50000,"High Value",IF(M32>=20000,"Medium Value","Low Value")) -> Medium Value | O32: =IF(AND(E32>=5,G32>=15%),"High",IF(OR(E32>=3,G32>=10%),"Medium","Low")) -> Medium | P32: =RIGHT(C32,3) -> 020 | Q32: =RIGHT(D32,3) -> 109 | R32: =PROPER(TRIM(J32)) -> Amit | S32: =TRIM(PROPER(I32)) -> South | T32: =IFERROR(VLOOKUP(D32,Product_Reference!$A$1:$F$26,2,0),"Not Found!!") -> Noise Cancelling Headphones | U32: =IFERROR(VLOOKUP(D32,Product_Reference!$A$1:$F$26,3,0),"Not Found!!") -> Audio | V32: =IFERROR(VLOOKUP(D32,Product_Reference!$A$1:$F$26,4,0),"Not Found!!") -> SoundMax | W32: =IFERROR(VLOOKUP(D32,Product_Reference!$A$1:$F$26,5,0),"Not Found!!") -> LMN Ltd | X32: =IFERROR(VLOOKUP(D32,Product_Reference!$A$1:$F$26,6,0),"Not Found!!") -> 4.7 | AA32: 8. Find the number of orders where Payment Mode is UPI and Region is East.
A33: ORD1032 | B33: 46093 | C33: C052 | D33: P103 | E33: 1 | F33: 65000 | G33: 0.1 | H33: Net Banking | I33: South | J33: Priya | K33: =PRODUCT(E33,F33) -> 65000 | L33: =PRODUCT(K33,G33) -> 6500 | M33: =K33-L33 -> 58500 | N33: =IF(M33>=50000,"High Value",IF(M33>=20000,"Medium Value","Low Value")) -> High Value | O33: =IF(AND(E33>=5,G33>=15%),"High",IF(OR(E33>=3,G33>=10%),"Medium","Low")) -> Medium | P33: =RIGHT(C33,3) -> 052 | Q33: =RIGHT(D33,3) -> 103 | R33: =PROPER(TRIM(J33)) -> Priya | S33: =TRIM(PROPER(I33)) -> South | T33: =IFERROR(VLOOKUP(D33,Product_Reference!$A$1:$F$26,2,0),"Not Found!!") -> Smartphone X | U33: =IFERROR(VLOOKUP(D33,Product_Reference!$A$1:$F$26,3,0),"Not Found!!") -> Electronics | V33: =IFERROR(VLOOKUP(D33,Product_Reference!$A$1:$F$26,4,0),"Not Found!!") -> MobileMax | W33: =IFERROR(VLOOKUP(D33,Product_Reference!$A$1:$F$26,5,0),"Not Found!!") -> ABC Ltd | X33: =IFERROR(VLOOKUP(D33,Product_Reference!$A$1:$F$26,6,0),"Not Found!!") -> 4.6 | AH33: Product_ID | AI33: Product Name | AJ33: Category | AK33: Brand | AL33: Supplier | AM33: Product Rating | AO33: P107
A34: ORD1033 | B34: 46079 | C34: C025 | D34: P108 | E34: 1 | F34: 7000 | G34: 0.08 | H34: UPI | I34: North | J34: Neha | K34: =PRODUCT(E34,F34) -> 7000 | L34: =PRODUCT(K34,G34) -> 560 | M34: =K34-L34 -> 6440 | N34: =IF(M34>=50000,"High Value",IF(M34>=20000,"Medium Value","Low Value")) -> Low Value | O34: =IF(AND(E34>=5,G34>=15%),"High",IF(OR(E34>=3,G34>=10%),"Medium","Low")) -> Low | P34: =RIGHT(C34,3) -> 025 | Q34: =RIGHT(D34,3) -> 108 | R34: =PROPER(TRIM(J34)) -> Neha | S34: =TRIM(PROPER(I34)) -> North | T34: =IFERROR(VLOOKUP(D34,Product_Reference!$A$1:$F$26,2,0),"Not Found!!") -> Smart Watch | U34: =IFERROR(VLOOKUP(D34,Product_Reference!$A$1:$F$26,3,0),"Not Found!!") -> Wearables | V34: =IFERROR(VLOOKUP(D34,Product_Reference!$A$1:$F$26,4,0),"Not Found!!") -> FitTech | W34: =IFERROR(VLOOKUP(D34,Product_Reference!$A$1:$F$26,5,0),"Not Found!!") -> ABC Ltd | X34: =IFERROR(VLOOKUP(D34,Product_Reference!$A$1:$F$26,6,0),"Not Found!!") -> 4 | AA34: Payment_Mode | AB34: Region | AC34: No. of Orders | AH34: P107 | AI34: {=IFERROR(VLOOKUP(AH34,Product_Reference!$A$1:$F$26,{2,3,4,5,6},0),"Not Found!!")} -> USB-C Hub | AJ34: Accessories | AK34: ConnectPro | AL34: PQR Ltd | AM34: 4.3 | AO34: P119
A35: ORD1034 | B35: 46038 | C35: C026 | D35: P110 | E35: 1 | F35: 9000 | G35: 0.18 | H35: Net Banking | I35: South | J35: Sneha | K35: =PRODUCT(E35,F35) -> 9000 | L35: =PRODUCT(K35,G35) -> 1620 | M35: =K35-L35 -> 7380 | N35: =IF(M35>=50000,"High Value",IF(M35>=20000,"Medium Value","Low Value")) -> Low Value | O35: =IF(AND(E35>=5,G35>=15%),"High",IF(OR(E35>=3,G35>=10%),"Medium","Low")) -> Medium | P35: =RIGHT(C35,3) -> 026 | Q35: =RIGHT(D35,3) -> 110 | R35: =PROPER(TRIM(J35)) -> Sneha | S35: =TRIM(PROPER(I35)) -> South | T35: =IFERROR(VLOOKUP(D35,Product_Reference!$A$1:$F$26,2,0),"Not Found!!") -> External SSD 1TB | U35: =IFERROR(VLOOKUP(D35,Product_Reference!$A$1:$F$26,3,0),"Not Found!!") -> Storage | V35: =IFERROR(VLOOKUP(D35,Product_Reference!$A$1:$F$26,4,0),"Not Found!!") -> DataDrive | W35: =IFERROR(VLOOKUP(D35,Product_Reference!$A$1:$F$26,5,0),"Not Found!!") -> PQR Ltd | X35: =IFERROR(VLOOKUP(D35,Product_Reference!$A$1:$F$26,6,0),"Not Found!!") -> 4.5 | AA35: UPI | AB35: East | AC35: =COUNTIFS(H2:H151,AA35,S2:S151,AB35) -> 14 | AO35: P122
A36: ORD1035 | B36: 46070 | C36: C012 | D36: P117 | E36: 1 | F36: 1800 | G36: 0 | H36: Card | I36: South | J36: Amit | K36: =PRODUCT(E36,F36) -> 1800 | L36: =PRODUCT(K36,G36) -> 0 | M36: =K36-L36 -> 1800 | N36: =IF(M36>=50000,"High Value",IF(M36>=20000,"Medium Value","Low Value")) -> Low Value | O36: =IF(AND(E36>=5,G36>=15%),"High",IF(OR(E36>=3,G36>=10%),"Medium","Low")) -> Low | P36: =RIGHT(C36,3) -> 012 | Q36: =RIGHT(D36,3) -> 117 | R36: =PROPER(TRIM(J36)) -> Amit | S36: =TRIM(PROPER(I36)) -> South | T36: =IFERROR(VLOOKUP(D36,Product_Reference!$A$1:$F$26,2,0),"Not Found!!") -> Laptop Stand | U36: =IFERROR(VLOOKUP(D36,Product_Reference!$A$1:$F$26,3,0),"Not Found!!") -> Accessories | V36: =IFERROR(VLOOKUP(D36,Product_Reference!$A$1:$F$26,4,0),"Not Found!!") -> ErgoTech | W36: =IFERROR(VLOOKUP(D36,Product_Reference!$A$1:$F$26,5,0),"Not Found!!") -> PQR Ltd | X36: =IFERROR(VLOOKUP(D36,Product_Reference!$A$1:$F$26,6,0),"Not Found!!") -> 4 | AO36: P121
A37: ORD1036 | B37: 46041 | C37: C014 | D37: P123 | E37: 5 | F37: 2800 | G37: 0 | H37: Net Banking | I37: South | J37: Neha | K37: =PRODUCT(E37,F37) -> 14000 | L37: =PRODUCT(K37,G37) -> 0 | M37: =K37-L37 -> 14000 | N37: =IF(M37>=50000,"High Value",IF(M37>=20000,"Medium Value","Low Value")) -> Low Value | O37: =IF(AND(E37>=5,G37>=15%),"High",IF(OR(E37>=3,G37>=10%),"Medium","Low")) -> Medium | P37: =RIGHT(C37,3) -> 14 | Q37: =RIGHT(D37,3) -> 123 | R37: =PROPER(TRIM(J37)) -> Neha | S37: =TRIM(PROPER(I37)) -> South | T37: =IFERROR(VLOOKUP(D37,Product_Reference!$A$1:$F$26,2,0),"Not Found!!") -> Wi-Fi Range Extender | U37: =IFERROR(VLOOKUP(D37,Product_Reference!$A$1:$F$26,3,0),"Not Found!!") -> Networking | V37: =IFERROR(VLOOKUP(D37,Product_Reference!$A$1:$F$26,4,0),"Not Found!!") -> NetLink | W37: =IFERROR(VLOOKUP(D37,Product_Reference!$A$1:$F$26,5,0),"Not Found!!") -> XYZ Ltd | X37: =IFERROR(VLOOKUP(D37,Product_Reference!$A$1:$F$26,6,0),"Not Found!!") -> 4 | AA37: 9. Find the number of orders where Quantity is greater than or equal to 3 and Discount is greater than or equal to 10%. | AO37: P110
A38: ORD1037 | B38: 46097 | C38: C049 | D38: P124 | E38: 1 | F38: 2500 | G38: 0.2 | H38: UPI | I38: West | J38: Sneha | K38: =PRODUCT(E38,F38) -> 2500 | L38: =PRODUCT(K38,G38) -> 500 | M38: =K38-L38 -> 2000 | N38: =IF(M38>=50000,"High Value",IF(M38>=20000,"Medium Value","Low Value")) -> Low Value | O38: =IF(AND(E38>=5,G38>=15%),"High",IF(OR(E38>=3,G38>=10%),"Medium","Low")) -> Medium | P38: =RIGHT(C38,3) -> 049 | Q38: =RIGHT(D38,3) -> 124 | R38: =PROPER(TRIM(J38)) -> Sneha | S38: =TRIM(PROPER(I38)) -> West | T38: =IFERROR(VLOOKUP(D38,Product_Reference!$A$1:$F$26,2,0),"Not Found!!") -> Tablet Keyboard | U38: =IFERROR(VLOOKUP(D38,Product_Reference!$A$1:$F$26,3,0),"Not Found!!") -> Accessories | V38: =IFERROR(VLOOKUP(D38,Product_Reference!$A$1:$F$26,4,0),"Not Found!!") -> KeyMaster | W38: =IFERROR(VLOOKUP(D38,Product_Reference!$A$1:$F$26,5,0),"Not Found!!") -> PQR Ltd | X38: =IFERROR(VLOOKUP(D38,Product_Reference!$A$1:$F$26,6,0),"Not Found!!") -> 3.8 | AO38: P114
A39: ORD1038 | B39: 46047 | C39: C029 | D39: P103 | E39: 5 | F39: 65000 | G39: 0.08 | H39: UPI | I39: West | J39: Priya | K39: =PRODUCT(E39,F39) -> 325000 | L39: =PRODUCT(K39,G39) -> 26000 | M39: =K39-L39 -> 299000 | N39: =IF(M39>=50000,"High Value",IF(M39>=20000,"Medium Value","Low Value")) -> High Value | O39: =IF(AND(E39>=5,G39>=15%),"High",IF(OR(E39>=3,G39>=10%),"Medium","Low")) -> Medium | P39: =RIGHT(C39,3) -> 029 | Q39: =RIGHT(D39,3) -> 103 | R39: =PROPER(TRIM(J39)) -> Priya | S39: =TRIM(PROPER(I39)) -> West | T39: =IFERROR(VLOOKUP(D39,Product_Reference!$A$1:$F$26,2,0),"Not Found!!") -> Smartphone X | U39: =IFERROR(VLOOKUP(D39,Product_Reference!$A$1:$F$26,3,0),"Not Found!!") -> Electronics | V39: =IFERROR(VLOOKUP(D39,Product_Reference!$A$1:$F$26,4,0),"Not Found!!") -> MobileMax | W39: =IFERROR(VLOOKUP(D39,Product_Reference!$A$1:$F$26,5,0),"Not Found!!") -> ABC Ltd | X39: =IFERROR(VLOOKUP(D39,Product_Reference!$A$1:$F$26,6,0),"Not Found!!") -> 4.6 | AA39: No. of Orders | AB39: =COUNTIFS(E2:E151,">=3",G2:G151,">=10%") -> 40 | AO39: P115
A40: ORD1039 | B40: 46102 | C40: C041 | D40: P102 | E40: 3 | F40: 1200 | G40: 0.08 | H40: UPI | I40: South | J40: Rahul | K40: =PRODUCT(E40,F40) -> 3600 | L40: =PRODUCT(K40,G40) -> 288 | M40: =K40-L40 -> 3312 | N40: =IF(M40>=50000,"High Value",IF(M40>=20000,"Medium Value","Low Value")) -> Low Value | O40: =IF(AND(E40>=5,G40>=15%),"High",IF(OR(E40>=3,G40>=10%),"Medium","Low")) -> Medium | P40: =RIGHT(C40,3) -> 041 | Q40: =RIGHT(D40,3) -> 102 | R40: =PROPER(TRIM(J40)) -> Rahul | S40: =TRIM(PROPER(I40)) -> South | T40: =IFERROR(VLOOKUP(D40,Product_Reference!$A$1:$F$26,2,0),"Not Found!!") -> Wireless Mouse | U40: =IFERROR(VLOOKUP(D40,Product_Reference!$A$1:$F$26,3,0),"Not Found!!") -> Accessories | V40: =IFERROR(VLOOKUP(D40,Product_Reference!$A$1:$F$26,4,0),"Not Found!!") -> ClickTech | W40: =IFERROR(VLOOKUP(D40,Product_Reference!$A$1:$F$26,5,0),"Not Found!!") -> XYZ Ltd | X40: =IFERROR(VLOOKUP(D40,Product_Reference!$A$1:$F$26,6,0),"Not Found!!") -> 4.2 | AO40: P118
A41: ORD1040 | B41: 46042 | C41: C056 | D41: P114 | E41: 2 | F41: 2500 | G41: 0.2 | H41: Card | I41: North | J41: Amit | K41: =PRODUCT(E41,F41) -> 5000 | L41: =PRODUCT(K41,G41) -> 1000 | M41: =K41-L41 -> 4000 | N41: =IF(M41>=50000,"High Value",IF(M41>=20000,"Medium Value","Low Value")) -> Low Value | O41: =IF(AND(E41>=5,G41>=15%),"High",IF(OR(E41>=3,G41>=10%),"Medium","Low")) -> Medium | P41: =RIGHT(C41,3) -> 056 | Q41: =RIGHT(D41,3) -> 114 | R41: =PROPER(TRIM(J41)) -> Amit | S41: =TRIM(PROPER(I41)) -> North | T41: =IFERROR(VLOOKUP(D41,Product_Reference!$A$1:$F$26,2,0),"Not Found!!") -> Power Bank 20000mAh | U41: =IFERROR(VLOOKUP(D41,Product_Reference!$A$1:$F$26,3,0),"Not Found!!") -> Accessories | V41: =IFERROR(VLOOKUP(D41,Product_Reference!$A$1:$F$26,4,0),"Not Found!!") -> PowerPlus | W41: =IFERROR(VLOOKUP(D41,Product_Reference!$A$1:$F$26,5,0),"Not Found!!") -> PQR Ltd | X41: =IFERROR(VLOOKUP(D41,Product_Reference!$A$1:$F$26,6,0),"Not Found!!") -> 4.1 | AA41: 10. Find the number of orders handled by each salesperson. | AO41: P123
A42: ORD1041 | B42: 46098 | C42: C059 | D42: P117 | E42: 1 | F42: 1800 | G42: 0.2 | H42: UPI | I42: North | J42: Neha | K42: =PRODUCT(E42,F42) -> 1800 | L42: =PRODUCT(K42,G42) -> 360 | M42: =K42-L42 -> 1440 | N42: =IF(M42>=50000,"High Value",IF(M42>=20000,"Medium Value","Low Value")) -> Low Value | O42: =IF(AND(E42>=5,G42>=15%),"High",IF(OR(E42>=3,G42>=10%),"Medium","Low")) -> Medium | P42: =RIGHT(C42,3) -> 059 | Q42: =RIGHT(D42,3) -> 117 | R42: =PROPER(TRIM(J42)) -> Neha | S42: =TRIM(PROPER(I42)) -> North | T42: =IFERROR(VLOOKUP(D42,Product_Reference!$A$1:$F$26,2,0),"Not Found!!") -> Laptop Stand | U42: =IFERROR(VLOOKUP(D42,Product_Reference!$A$1:$F$26,3,0),"Not Found!!") -> Accessories | V42: =IFERROR(VLOOKUP(D42,Product_Reference!$A$1:$F$26,4,0),"Not Found!!") -> ErgoTech | W42: =IFERROR(VLOOKUP(D42,Product_Reference!$A$1:$F$26,5,0),"Not Found!!") -> PQR Ltd | X42: =IFERROR(VLOOKUP(D42,Product_Reference!$A$1:$F$26,6,0),"Not Found!!") -> 4 | AO42: P124
A43: ORD1042 | B43: 46073 | C43: C054 | D43: P114 | E43: 3 | F43: 2500 | G43: 0.15 | H43: Net Banking | I43: north | J43: Priya | K43: =PRODUCT(E43,F43) -> 7500 | L43: =PRODUCT(K43,G43) -> 1125 | M43: =K43-L43 -> 6375 | N43: =IF(M43>=50000,"High Value",IF(M43>=20000,"Medium Value","Low Value")) -> Low Value | O43: =IF(AND(E43>=5,G43>=15%),"High",IF(OR(E43>=3,G43>=10%),"Medium","Low")) -> Medium | P43: =RIGHT(C43,3) -> 054 | Q43: =RIGHT(D43,3) -> 114 | R43: =PROPER(TRIM(J43)) -> Priya | S43: =TRIM(PROPER(I43)) -> North | T43: =IFERROR(VLOOKUP(D43,Product_Reference!$A$1:$F$26,2,0),"Not Found!!") -> Power Bank 20000mAh | U43: =IFERROR(VLOOKUP(D43,Product_Reference!$A$1:$F$26,3,0),"Not Found!!") -> Accessories | V43: =IFERROR(VLOOKUP(D43,Product_Reference!$A$1:$F$26,4,0),"Not Found!!") -> PowerPlus | W43: =IFERROR(VLOOKUP(D43,Product_Reference!$A$1:$F$26,5,0),"Not Found!!") -> PQR Ltd | X43: =IFERROR(VLOOKUP(D43,Product_Reference!$A$1:$F$26,6,0),"Not Found!!") -> 4.1 | AA43: Salesperson | AB43: No.of Orders | AO43: P101
A44: ORD1043 | B44: 46086 | C44: C033 | D44: P121 | E44: 1 | F44: 30000 | G44: 0.1 | H44: UPI | I44: East | J44: Amit | K44: =PRODUCT(E44,F44) -> 30000 | L44: =PRODUCT(K44,G44) -> 3000 | M44: =K44-L44 -> 27000 | N44: =IF(M44>=50000,"High Value",IF(M44>=20000,"Medium Value","Low Value")) -> Medium Value | O44: =IF(AND(E44>=5,G44>=15%),"High",IF(OR(E44>=3,G44>=10%),"Medium","Low")) -> Medium | P44: =RIGHT(C44,3) -> 033 | Q44: =RIGHT(D44,3) -> 121 | R44: =PROPER(TRIM(J44)) -> Amit | S44: =TRIM(PROPER(I44)) -> East | T44: =IFERROR(VLOOKUP(D44,Product_Reference!$A$1:$F$26,2,0),"Not Found!!") -> Portable Projector | U44: =IFERROR(VLOOKUP(D44,Product_Reference!$A$1:$F$26,3,0),"Not Found!!") -> Electronics | V44: =IFERROR(VLOOKUP(D44,Product_Reference!$A$1:$F$26,4,0),"Not Found!!") -> ViewMax | W44: =IFERROR(VLOOKUP(D44,Product_Reference!$A$1:$F$26,5,0),"Not Found!!") -> PQR Ltd | X44: =IFERROR(VLOOKUP(D44,Product_Reference!$A$1:$F$26,6,0),"Not Found!!") -> 4.1 | AA44: Sneha | AB44: =COUNTIF(R2:R151,AA44) -> 26 | AO44: P103
A45: ORD1044 | B45: 46071 | C45: C017 | D45: P104 | E45: 1 | F45: 28000 | G45: 0.2 | H45: Net Banking | I45: West | J45: Karan | K45: =PRODUCT(E45,F45) -> 28000 | L45: =PRODUCT(K45,G45) -> 5600 | M45: =K45-L45 -> 22400 | N45: =IF(M45>=50000,"High Value",IF(M45>=20000,"Medium Value","Low Value")) -> Medium Value | O45: =IF(AND(E45>=5,G45>=15%),"High",IF(OR(E45>=3,G45>=10%),"Medium","Low")) -> Medium | P45: =RIGHT(C45,3) -> 017 | Q45: =RIGHT(D45,3) -> 104 | R45: =PROPER(TRIM(J45)) -> Karan | S45: =TRIM(PROPER(I45)) -> West | T45: =IFERROR(VLOOKUP(D45,Product_Reference!$A$1:$F$26,2,0),"Not Found!!") -> Tablet 10 | U45: =IFERROR(VLOOKUP(D45,Product_Reference!$A$1:$F$26,3,0),"Not Found!!") -> Electronics | V45: =IFERROR(VLOOKUP(D45,Product_Reference!$A$1:$F$26,4,0),"Not Found!!") -> TabWorld | W45: =IFERROR(VLOOKUP(D45,Product_Reference!$A$1:$F$26,5,0),"Not Found!!") -> PQR Ltd | X45: =IFERROR(VLOOKUP(D45,Product_Reference!$A$1:$F$26,6,0),"Not Found!!") -> 4.1 | AO45: P113
A46: ORD1045 | B46: 46059 | C46: C024 | D46: P114 | E46: 2 | F46: 2500 | G46: 0.15 | H46: UPI | I46: West | J46: Karan | K46: =PRODUCT(E46,F46) -> 5000 | L46: =PRODUCT(K46,G46) -> 750 | M46: =K46-L46 -> 4250 | N46: =IF(M46>=50000,"High Value",IF(M46>=20000,"Medium Value","Low Value")) -> Low Value | O46: =IF(AND(E46>=5,G46>=15%),"High",IF(OR(E46>=3,G46>=10%),"Medium","Low")) -> Medium | P46: =RIGHT(C46,3) -> 024 | Q46: =RIGHT(D46,3) -> 114 | R46: =PROPER(TRIM(J46)) -> Karan | S46: =TRIM(PROPER(I46)) -> West | T46: =IFERROR(VLOOKUP(D46,Product_Reference!$A$1:$F$26,2,0),"Not Found!!") -> Power Bank 20000mAh | U46: =IFERROR(VLOOKUP(D46,Product_Reference!$A$1:$F$26,3,0),"Not Found!!") -> Accessories | V46: =IFERROR(VLOOKUP(D46,Product_Reference!$A$1:$F$26,4,0),"Not Found!!") -> PowerPlus | W46: =IFERROR(VLOOKUP(D46,Product_Reference!$A$1:$F$26,5,0),"Not Found!!") -> PQR Ltd | X46: =IFERROR(VLOOKUP(D46,Product_Reference!$A$1:$F$26,6,0),"Not Found!!") -> 4.1 | AO46: P102
A47: ORD1046 | B47: 46085 | C47: C021 | D47: P103 | E47: 1 | F47: 65000 | G47: 0.1 | H47: UPI | I47: East | J47: Amit | K47: =PRODUCT(E47,F47) -> 65000 | L47: =PRODUCT(K47,G47) -> 6500 | M47: =K47-L47 -> 58500 | N47: =IF(M47>=50000,"High Value",IF(M47>=20000,"Medium Value","Low Value")) -> High Value | O47: =IF(AND(E47>=5,G47>=15%),"High",IF(OR(E47>=3,G47>=10%),"Medium","Low")) -> Medium | P47: =RIGHT(C47,3) -> 021 | Q47: =RIGHT(D47,3) -> 103 | R47: =PROPER(TRIM(J47)) -> Amit | S47: =TRIM(PROPER(I47)) -> East | T47: =IFERROR(VLOOKUP(D47,Product_Reference!$A$1:$F$26,2,0),"Not Found!!") -> Smartphone X | U47: =IFERROR(VLOOKUP(D47,Product_Reference!$A$1:$F$26,3,0),"Not Found!!") -> Electronics | V47: =IFERROR(VLOOKUP(D47,Product_Reference!$A$1:$F$26,4,0),"Not Found!!") -> MobileMax | W47: =IFERROR(VLOOKUP(D47,Product_Reference!$A$1:$F$26,5,0),"Not Found!!") -> ABC Ltd | X47: =IFERROR(VLOOKUP(D47,Product_Reference!$A$1:$F$26,6,0),"Not Found!!") -> 4.6 | AO47: P112
A48: ORD1047 | B48: 46076 | C48: C058 | D48: P118 | E48: 5 | F48: 650 | G48: 0.05 | H48: Net Banking | I48: West | J48: Priya | K48: =PRODUCT(E48,F48) -> 3250 | L48: =PRODUCT(K48,G48) -> 162.5 | M48: =K48-L48 -> 3087.5 | N48: =IF(M48>=50000,"High Value",IF(M48>=20000,"Medium Value","Low Value")) -> Low Value | O48: =IF(AND(E48>=5,G48>=15%),"High",IF(OR(E48>=3,G48>=10%),"Medium","Low")) -> Medium | P48: =RIGHT(C48,3) -> 058 | Q48: =RIGHT(D48,3) -> 118 | R48: =PROPER(TRIM(J48)) -> Priya | S48: =TRIM(PROPER(I48)) -> West | T48: =IFERROR(VLOOKUP(D48,Product_Reference!$A$1:$F$26,2,0),"Not Found!!") -> Mechanical Pencil Set | U48: =IFERROR(VLOOKUP(D48,Product_Reference!$A$1:$F$26,3,0),"Not Found!!") -> Stationery | V48: =IFERROR(VLOOKUP(D48,Product_Reference!$A$1:$F$26,4,0),"Not Found!!") -> WriteWell | W48: =IFERROR(VLOOKUP(D48,Product_Reference!$A$1:$F$26,5,0),"Not Found!!") -> LMN Ltd | X48: =IFERROR(VLOOKUP(D48,Product_Reference!$A$1:$F$26,6,0),"Not Found!!") -> 4.3 | AO48: P125
A49: ORD1048 | B49: 46088 | C49: C027 | D49: P115 | E49: 3 | F49: 42000 | G49: 0.18 | H49: UPI | I49: West | J49: Rahul | K49: =PRODUCT(E49,F49) -> 126000 | L49: =PRODUCT(K49,G49) -> 22680 | M49: =K49-L49 -> 103320 | N49: =IF(M49>=50000,"High Value",IF(M49>=20000,"Medium Value","Low Value")) -> High Value | O49: =IF(AND(E49>=5,G49>=15%),"High",IF(OR(E49>=3,G49>=10%),"Medium","Low")) -> Medium | P49: =RIGHT(C49,3) -> 027 | Q49: =RIGHT(D49,3) -> 115 | R49: =PROPER(TRIM(J49)) -> Rahul | S49: =TRIM(PROPER(I49)) -> West | T49: =IFERROR(VLOOKUP(D49,Product_Reference!$A$1:$F$26,2,0),"Not Found!!") -> Smart TV 43 | U49: =IFERROR(VLOOKUP(D49,Product_Reference!$A$1:$F$26,3,0),"Not Found!!") -> Electronics | V49: =IFERROR(VLOOKUP(D49,Product_Reference!$A$1:$F$26,4,0),"Not Found!!") -> ViewMax | W49: =IFERROR(VLOOKUP(D49,Product_Reference!$A$1:$F$26,5,0),"Not Found!!") -> ABC Ltd | X49: =IFERROR(VLOOKUP(D49,Product_Reference!$A$1:$F$26,6,0),"Not Found!!") -> 4.6 | AO49: P120
A50: ORD1049 | B50: 46065 | C50: C054 | D50: P108 | E50: 1 | F50: 7000 | G50: 0 | H50: UPI | I50: East | J50: Priya | K50: =PRODUCT(E50,F50) -> 7000 | L50: =PRODUCT(K50,G50) -> 0 | M50: =K50-L50 -> 7000 | N50: =IF(M50>=50000,"High Value",IF(M50>=20000,"Medium Value","Low Value")) -> Low Value | O50: =IF(AND(E50>=5,G50>=15%),"High",IF(OR(E50>=3,G50>=10%),"Medium","Low")) -> Low | P50: =RIGHT(C50,3) -> 054 | Q50: =RIGHT(D50,3) -> 108 | R50: =PROPER(TRIM(J50)) -> Priya | S50: =TRIM(PROPER(I50)) -> East | T50: =IFERROR(VLOOKUP(D50,Product_Reference!$A$1:$F$26,2,0),"Not Found!!") -> Smart Watch | U50: =IFERROR(VLOOKUP(D50,Product_Reference!$A$1:$F$26,3,0),"Not Found!!") -> Wearables | V50: =IFERROR(VLOOKUP(D50,Product_Reference!$A$1:$F$26,4,0),"Not Found!!") -> FitTech | W50: =IFERROR(VLOOKUP(D50,Product_Reference!$A$1:$F$26,5,0),"Not Found!!") -> ABC Ltd | X50: =IFERROR(VLOOKUP(D50,Product_Reference!$A$1:$F$26,6,0),"Not Found!!") -> 4 | AO50: P106
A51: ORD1050 | B51: 46072 | C51: C025 | D51: P123 | E51: 6 | F51: 2800 | G51: 0.08 | H51: Card | I51: South | J51: Priya | K51: =PRODUCT(E51,F51) -> 16800 | L51: =PRODUCT(K51,G51) -> 1344 | M51: =K51-L51 -> 15456 | N51: =IF(M51>=50000,"High Value",IF(M51>=20000,"Medium Value","Low Value")) -> Low Value | O51: =IF(AND(E51>=5,G51>=15%),"High",IF(OR(E51>=3,G51>=10%),"Medium","Low")) -> Medium | P51: =RIGHT(C51,3) -> 025 | Q51: =RIGHT(D51,3) -> 123 | R51: =PROPER(TRIM(J51)) -> Priya | S51: =TRIM(PROPER(I51)) -> South | T51: =IFERROR(VLOOKUP(D51,Product_Reference!$A$1:$F$26,2,0),"Not Found!!") -> Wi-Fi Range Extender | U51: =IFERROR(VLOOKUP(D51,Product_Reference!$A$1:$F$26,3,0),"Not Found!!") -> Networking | V51: =IFERROR(VLOOKUP(D51,Product_Reference!$A$1:$F$26,4,0),"Not Found!!") -> NetLink | W51: =IFERROR(VLOOKUP(D51,Product_Reference!$A$1:$F$26,5,0),"Not Found!!") -> XYZ Ltd | X51: =IFERROR(VLOOKUP(D51,Product_Reference!$A$1:$F$26,6,0),"Not Found!!") -> 4 | AO51: P109
A52: ORD1051 | B52: 46067 | C52: C020 | D52: P107 | E52: 5 | F52: 2200 | G52: 0.1 | H52: Card | I52: South | J52: Neha | K52: =PRODUCT(E52,F52) -> 11000 | L52: =PRODUCT(K52,G52) -> 1100 | M52: =K52-L52 -> 9900 | N52: =IF(M52>=50000,"High Value",IF(M52>=20000,"Medium Value","Low Value")) -> Low Value | O52: =IF(AND(E52>=5,G52>=15%),"High",IF(OR(E52>=3,G52>=10%),"Medium","Low")) -> Medium | P52: =RIGHT(C52,3) -> 020 | Q52: =RIGHT(D52,3) -> 107 | R52: =PROPER(TRIM(J52)) -> Neha | S52: =TRIM(PROPER(I52)) -> South | T52: =IFERROR(VLOOKUP(D52,Product_Reference!$A$1:$F$26,2,0),"Not Found!!") -> USB-C Hub | U52: =IFERROR(VLOOKUP(D52,Product_Reference!$A$1:$F$26,3,0),"Not Found!!") -> Accessories | V52: =IFERROR(VLOOKUP(D52,Product_Reference!$A$1:$F$26,4,0),"Not Found!!") -> ConnectPro | W52: =IFERROR(VLOOKUP(D52,Product_Reference!$A$1:$F$26,5,0),"Not Found!!") -> PQR Ltd | X52: =IFERROR(VLOOKUP(D52,Product_Reference!$A$1:$F$26,6,0),"Not Found!!") -> 4.3 | AO52: P108
A53: ORD1052 | B53: 46037 | C53: C028 | D53: P116 | E53: 1 | F53: 3000 | G53: 0.18 | H53: Card | I53: South | J53: Neha | K53: =PRODUCT(E53,F53) -> 3000 | L53: =PRODUCT(K53,G53) -> 540 | M53: =K53-L53 -> 2460 | N53: =IF(M53>=50000,"High Value",IF(M53>=20000,"Medium Value","Low Value")) -> Low Value | O53: =IF(AND(E53>=5,G53>=15%),"High",IF(OR(E53>=3,G53>=10%),"Medium","Low")) -> Medium | P53: =RIGHT(C53,3) -> 028 | Q53: =RIGHT(D53,3) -> 116 | R53: =PROPER(TRIM(J53)) -> Neha | S53: =TRIM(PROPER(I53)) -> South | T53: =IFERROR(VLOOKUP(D53,Product_Reference!$A$1:$F$26,2,0),"Not Found!!") -> Fitness Band | U53: =IFERROR(VLOOKUP(D53,Product_Reference!$A$1:$F$26,3,0),"Not Found!!") -> Wearables | V53: =IFERROR(VLOOKUP(D53,Product_Reference!$A$1:$F$26,4,0),"Not Found!!") -> FitTech | W53: =IFERROR(VLOOKUP(D53,Product_Reference!$A$1:$F$26,5,0),"Not Found!!") -> XYZ Ltd | X53: =IFERROR(VLOOKUP(D53,Product_Reference!$A$1:$F$26,6,0),"Not Found!!") -> 3.7 | AO53: P117
A54: ORD1053 | B54: 46085 | C54: C022 | D54: P119 | F54: 12500 | G54: 0.05 | H54: Card | I54: West | J54: Rahul | K54: =PRODUCT(E54,F54) -> 12500 | L54: =PRODUCT(K54,G54) -> 625 | M54: =K54-L54 -> 11875 | N54: =IF(M54>=50000,"High Value",IF(M54>=20000,"Medium Value","Low Value")) -> Low Value | O54: =IF(AND(E54>=5,G54>=15%),"High",IF(OR(E54>=3,G54>=10%),"Medium","Low")) -> Low | P54: =RIGHT(C54,3) -> 022 | Q54: =RIGHT(D54,3) -> 119 | R54: =PROPER(TRIM(J54)) -> Rahul | S54: =TRIM(PROPER(I54)) -> West | T54: =IFERROR(VLOOKUP(D54,Product_Reference!$A$1:$F$26,2,0),"Not Found!!") -> Office Chair | U54: =IFERROR(VLOOKUP(D54,Product_Reference!$A$1:$F$26,3,0),"Not Found!!") -> Furniture | V54: =IFERROR(VLOOKUP(D54,Product_Reference!$A$1:$F$26,4,0),"Not Found!!") -> ComfortPro | W54: =IFERROR(VLOOKUP(D54,Product_Reference!$A$1:$F$26,5,0),"Not Found!!") -> ABC Ltd | X54: =IFERROR(VLOOKUP(D54,Product_Reference!$A$1:$F$26,6,0),"Not Found!!") -> 4.2 | AO54: P104
A55: ORD1054 | B55: 46037 | C55: C054 | D55: P120 | E55: 6 | F55: 2200 | G55: 0.15 | H55: Card | I55: East | J55: Rahul | K55: =PRODUCT(E55,F55) -> 13200 | L55: =PRODUCT(K55,G55) -> 1980 | M55: =K55-L55 -> 11220 | N55: =IF(M55>=50000,"High Value",IF(M55>=20000,"Medium Value","Low Value")) -> Low Value | O55: =IF(AND(E55>=5,G55>=15%),"High",IF(OR(E55>=3,G55>=10%),"Medium","Low")) -> High | P55: =RIGHT(C55,3) -> 054 | Q55: =RIGHT(D55,3) -> 120 | R55: =PROPER(TRIM(J55)) -> Rahul | S55: =TRIM(PROPER(I55)) -> East | T55: =IFERROR(VLOOKUP(D55,Product_Reference!$A$1:$F$26,2,0),"Not Found!!") -> Desk Lamp | U55: =IFERROR(VLOOKUP(D55,Product_Reference!$A$1:$F$26,3,0),"Not Found!!") -> Furniture | V55: =IFERROR(VLOOKUP(D55,Product_Reference!$A$1:$F$26,4,0),"Not Found!!") -> BrightHome | W55: =IFERROR(VLOOKUP(D55,Product_Reference!$A$1:$F$26,5,0),"Not Found!!") -> XYZ Ltd | X55: =IFERROR(VLOOKUP(D55,Product_Reference!$A$1:$F$26,6,0),"Not Found!!") -> 3.9 | AO55: P116
A56: ORD1055 | B56: 46027 | C56: C039 | D56: P108 | E56: 2 | F56: 7000 | G56: 0.1 | H56: UPI | I56: East | J56: Sneha | K56: =PRODUCT(E56,F56) -> 14000 | L56: =PRODUCT(K56,G56) -> 1400 | M56: =K56-L56 -> 12600 | N56: =IF(M56>=50000,"High Value",IF(M56>=20000,"Medium Value","Low Value")) -> Low Value | O56: =IF(AND(E56>=5,G56>=15%),"High",IF(OR(E56>=3,G56>=10%),"Medium","Low")) -> Medium | P56: =RIGHT(C56,3) -> 039 | Q56: =RIGHT(D56,3) -> 108 | R56: =PROPER(TRIM(J56)) -> Sneha | S56: =TRIM(PROPER(I56)) -> East | T56: =IFERROR(VLOOKUP(D56,Product_Reference!$A$1:$F$26,2,0),"Not Found!!") -> Smart Watch | U56: =IFERROR(VLOOKUP(D56,Product_Reference!$A$1:$F$26,3,0),"Not Found!!") -> Wearables | V56: =IFERROR(VLOOKUP(D56,Product_Reference!$A$1:$F$26,4,0),"Not Found!!") -> FitTech | W56: =IFERROR(VLOOKUP(D56,Product_Reference!$A$1:$F$26,5,0),"Not Found!!") -> ABC Ltd | X56: =IFERROR(VLOOKUP(D56,Product_Reference!$A$1:$F$26,6,0),"Not Found!!") -> 4 | AO56: P105
A57: ORD1056 | B57: 46062 | C57: C052 | D57: P115 | E57: 1 | F57: 42000 | G57: 0.18 | H57: UPI | I57: West | J57: Sneha | K57: =PRODUCT(E57,F57) -> 42000 | L57: =PRODUCT(K57,G57) -> 7560 | M57: =K57-L57 -> 34440 | N57: =IF(M57>=50000,"High Value",IF(M57>=20000,"Medium Value","Low Value")) -> Medium Value | O57: =IF(AND(E57>=5,G57>=15%),"High",IF(OR(E57>=3,G57>=10%),"Medium","Low")) -> Medium | P57: =RIGHT(C57,3) -> 052 | Q57: =RIGHT(D57,3) -> 115 | R57: =PROPER(TRIM(J57)) -> Sneha | S57: =TRIM(PROPER(I57)) -> West | T57: =IFERROR(VLOOKUP(D57,Product_Reference!$A$1:$F$26,2,0),"Not Found!!") -> Smart TV 43 | U57: =IFERROR(VLOOKUP(D57,Product_Reference!$A$1:$F$26,3,0),"Not Found!!") -> Electronics | V57: =IFERROR(VLOOKUP(D57,Product_Reference!$A$1:$F$26,4,0),"Not Found!!") -> ViewMax | W57: =IFERROR(VLOOKUP(D57,Product_Reference!$A$1:$F$26,5,0),"Not Found!!") -> ABC Ltd | X57: =IFERROR(VLOOKUP(D57,Product_Reference!$A$1:$F$26,6,0),"Not Found!!") -> 4.6 | AO57: P111
A58: ORD1057 | B58: 46085 | C58: C019 | D58: P110 | E58: 1 | F58: 9000 | G58: 0 | H58: Card | I58: North | J58: Priya | K58: =PRODUCT(E58,F58) -> 9000 | L58: =PRODUCT(K58,G58) -> 0 | M58: =K58-L58 -> 9000 | N58: =IF(M58>=50000,"High Value",IF(M58>=20000,"Medium Value","Low Value")) -> Low Value | O58: =IF(AND(E58>=5,G58>=15%),"High",IF(OR(E58>=3,G58>=10%),"Medium","Low")) -> Low | P58: =RIGHT(C58,3) -> 019 | Q58: =RIGHT(D58,3) -> 110 | R58: =PROPER(TRIM(J58)) -> Priya | S58: =TRIM(PROPER(I58)) -> North | T58: =IFERROR(VLOOKUP(D58,Product_Reference!$A$1:$F$26,2,0),"Not Found!!") -> External SSD 1TB | U58: =IFERROR(VLOOKUP(D58,Product_Reference!$A$1:$F$26,3,0),"Not Found!!") -> Storage | V58: =IFERROR(VLOOKUP(D58,Product_Reference!$A$1:$F$26,4,0),"Not Found!!") -> DataDrive | W58: =IFERROR(VLOOKUP(D58,Product_Reference!$A$1:$F$26,5,0),"Not Found!!") -> PQR Ltd | X58: =IFERROR(VLOOKUP(D58,Product_Reference!$A$1:$F$26,6,0),"Not Found!!") -> 4.5 | AO58: P108
A59: ORD1058 | B59: 46084 | C59: C023 | D59: P105 | E59: 6 | F59: 3500 | G59: 0.12 | H59: Card | I59: South | J59: Karan | K59: =PRODUCT(E59,F59) -> 21000 | L59: =PRODUCT(K59,G59) -> 2520 | M59: =K59-L59 -> 18480 | N59: =IF(M59>=50000,"High Value",IF(M59>=20000,"Medium Value","Low Value")) -> Low Value | O59: =IF(AND(E59>=5,G59>=15%),"High",IF(OR(E59>=3,G59>=10%),"Medium","Low")) -> Medium | P59: =RIGHT(C59,3) -> 023 | Q59: =RIGHT(D59,3) -> 105 | R59: =PROPER(TRIM(J59)) -> Karan | S59: =TRIM(PROPER(I59)) -> South | T59: =IFERROR(VLOOKUP(D59,Product_Reference!$A$1:$F$26,2,0),"Not Found!!") -> Mechanical Keyboard | U59: =IFERROR(VLOOKUP(D59,Product_Reference!$A$1:$F$26,3,0),"Not Found!!") -> Accessories | V59: =IFERROR(VLOOKUP(D59,Product_Reference!$A$1:$F$26,4,0),"Not Found!!") -> KeyMaster | W59: =IFERROR(VLOOKUP(D59,Product_Reference!$A$1:$F$26,5,0),"Not Found!!") -> XYZ Ltd | X59: =IFERROR(VLOOKUP(D59,Product_Reference!$A$1:$F$26,6,0),"Not Found!!") -> 4.4 | AO59: P121
A60: ORD1059 | B60: 46023 | C60: C047 | D60: P101 | E60: 6 | F60: 45000 | G60: 0.05 | H60: UPI | I60: West | J60: Neha | K60: =PRODUCT(E60,F60) -> 270000 | L60: =PRODUCT(K60,G60) -> 13500 | M60: =K60-L60 -> 256500 | N60: =IF(M60>=50000,"High Value",IF(M60>=20000,"Medium Value","Low Value")) -> High Value | O60: =IF(AND(E60>=5,G60>=15%),"High",IF(OR(E60>=3,G60>=10%),"Medium","Low")) -> Medium | P60: =RIGHT(C60,3) -> 047 | Q60: =RIGHT(D60,3) -> 101 | R60: =PROPER(TRIM(J60)) -> Neha | S60: =TRIM(PROPER(I60)) -> West | T60: =IFERROR(VLOOKUP(D60,Product_Reference!$A$1:$F$26,2,0),"Not Found!!") -> Laptop Pro 14 | U60: =IFERROR(VLOOKUP(D60,Product_Reference!$A$1:$F$26,3,0),"Not Found!!") -> Electronics | V60: =IFERROR(VLOOKUP(D60,Product_Reference!$A$1:$F$26,4,0),"Not Found!!") -> TechPro | W60: =IFERROR(VLOOKUP(D60,Product_Reference!$A$1:$F$26,5,0),"Not Found!!") -> ABC Ltd | X60: =IFERROR(VLOOKUP(D60,Product_Reference!$A$1:$F$26,6,0),"Not Found!!") -> 4.5
A61: ORD1060 | B61: 46023 | C61: C016 | D61: P116 | E61: 5 | F61: 3000 | G61: 0.2 | H61: Card | I61: South | J61: Karan | K61: =PRODUCT(E61,F61) -> 15000 | L61: =PRODUCT(K61,G61) -> 3000 | M61: =K61-L61 -> 12000 | N61: =IF(M61>=50000,"High Value",IF(M61>=20000,"Medium Value","Low Value")) -> Low Value | O61: =IF(AND(E61>=5,G61>=15%),"High",IF(OR(E61>=3,G61>=10%),"Medium","Low")) -> High | P61: =RIGHT(C61,3) -> 016 | Q61: =RIGHT(D61,3) -> 116 | R61: =PROPER(TRIM(J61)) -> Karan | S61: =TRIM(PROPER(I61)) -> South | T61: =IFERROR(VLOOKUP(D61,Product_Reference!$A$1:$F$26,2,0),"Not Found!!") -> Fitness Band | U61: =IFERROR(VLOOKUP(D61,Product_Reference!$A$1:$F$26,3,0),"Not Found!!") -> Wearables | V61: =IFERROR(VLOOKUP(D61,Product_Reference!$A$1:$F$26,4,0),"Not Found!!") -> FitTech | W61: =IFERROR(VLOOKUP(D61,Product_Reference!$A$1:$F$26,5,0),"Not Found!!") -> XYZ Ltd | X61: =IFERROR(VLOOKUP(D61,Product_Reference!$A$1:$F$26,6,0),"Not Found!!") -> 3.7
A62: ORD1061 | B62: 46098 | C62: C026 | D62: P122 | E62: 3 | F62: 5500 | G62: 0.08 | H62: UPI | I62: East | J62: Neha | K62: =PRODUCT(E62,F62) -> 16500 | L62: =PRODUCT(K62,G62) -> 1320 | M62: =K62-L62 -> 15180 | N62: =IF(M62>=50000,"High Value",IF(M62>=20000,"Medium Value","Low Value")) -> Low Value | O62: =IF(AND(E62>=5,G62>=15%),"High",IF(OR(E62>=3,G62>=10%),"Medium","Low")) -> Medium | P62: =RIGHT(C62,3) -> 026 | Q62: =RIGHT(D62,3) -> 122 | R62: =PROPER(TRIM(J62)) -> Neha | S62: =TRIM(PROPER(I62)) -> East | T62: =IFERROR(VLOOKUP(D62,Product_Reference!$A$1:$F$26,2,0),"Not Found!!") -> Router AX1800 | U62: =IFERROR(VLOOKUP(D62,Product_Reference!$A$1:$F$26,3,0),"Not Found!!") -> Networking | V62: =IFERROR(VLOOKUP(D62,Product_Reference!$A$1:$F$26,4,0),"Not Found!!") -> NetLink | W62: =IFERROR(VLOOKUP(D62,Product_Reference!$A$1:$F$26,5,0),"Not Found!!") -> ABC Ltd | X62: =IFERROR(VLOOKUP(D62,Product_Reference!$A$1:$F$26,6,0),"Not Found!!") -> 4.5
A63: ORD1062 | B63: 46084 | C63: C052 | D63: P125 | E63: 2 | F63: 16000 | G63: 0.18 | H63: UPI | I63: South | J63: Priya | K63: =PRODUCT(E63,F63) -> 32000 | L63: =PRODUCT(K63,G63) -> 5760 | M63: =K63-L63 -> 26240 | N63: =IF(M63>=50000,"High Value",IF(M63>=20000,"Medium Value","Low Value")) -> Medium Value | O63: =IF(AND(E63>=5,G63>=15%),"High",IF(OR(E63>=3,G63>=10%),"Medium","Low")) -> Medium | P63: =RIGHT(C63,3) -> 052 | Q63: =RIGHT(D63,3) -> 125 | R63: =PROPER(TRIM(J63)) -> Priya | S63: =TRIM(PROPER(I63)) -> South | T63: =IFERROR(VLOOKUP(D63,Product_Reference!$A$1:$F$26,2,0),"Not Found!!") -> Laser Printer | U63: =IFERROR(VLOOKUP(D63,Product_Reference!$A$1:$F$26,3,0),"Not Found!!") -> Office Equipment | V63: =IFERROR(VLOOKUP(D63,Product_Reference!$A$1:$F$26,4,0),"Not Found!!") -> PrintPro | W63: =IFERROR(VLOOKUP(D63,Product_Reference!$A$1:$F$26,5,0),"Not Found!!") -> ABC Ltd | X63: =IFERROR(VLOOKUP(D63,Product_Reference!$A$1:$F$26,6,0),"Not Found!!") -> 4.2
A64: ORD1063 | B64: 46055 | C64: C030 | D64: P116 | E64: 2 | F64: 3000 | G64: 0.18 | H64: Card | I64: West | J64: Priya | K64: =PRODUCT(E64,F64) -> 6000 | L64: =PRODUCT(K64,G64) -> 1080 | M64: =K64-L64 -> 4920 | N64: =IF(M64>=50000,"High Value",IF(M64>=20000,"Medium Value","Low Value")) -> Low Value | O64: =IF(AND(E64>=5,G64>=15%),"High",IF(OR(E64>=3,G64>=10%),"Medium","Low")) -> Medium | P64: =RIGHT(C64,3) -> 030 | Q64: =RIGHT(D64,3) -> 116 | R64: =PROPER(TRIM(J64)) -> Priya | S64: =TRIM(PROPER(I64)) -> West | T64: =IFERROR(VLOOKUP(D64,Product_Reference!$A$1:$F$26,2,0),"Not Found!!") -> Fitness Band | U64: =IFERROR(VLOOKUP(D64,Product_Reference!$A$1:$F$26,3,0),"Not Found!!") -> Wearables | V64: =IFERROR(VLOOKUP(D64,Product_Reference!$A$1:$F$26,4,0),"Not Found!!") -> FitTech | W64: =IFERROR(VLOOKUP(D64,Product_Reference!$A$1:$F$26,5,0),"Not Found!!") -> XYZ Ltd | X64: =IFERROR(VLOOKUP(D64,Product_Reference!$A$1:$F$26,6,0),"Not Found!!") -> 3.7
A65: ORD1064 | B65: 46056 | C65: C052 | D65: P122 | E65: 2 | F65: 5500 | G65: 0.1 | H65: UPI | I65: West | J65: Amit | K65: =PRODUCT(E65,F65) -> 11000 | L65: =PRODUCT(K65,G65) -> 1100 | M65: =K65-L65 -> 9900 | N65: =IF(M65>=50000,"High Value",IF(M65>=20000,"Medium Value","Low Value")) -> Low Value | O65: =IF(AND(E65>=5,G65>=15%),"High",IF(OR(E65>=3,G65>=10%),"Medium","Low")) -> Medium | P65: =RIGHT(C65,3) -> 052 | Q65: =RIGHT(D65,3) -> 122 | R65: =PROPER(TRIM(J65)) -> Amit | S65: =TRIM(PROPER(I65)) -> West | T65: =IFERROR(VLOOKUP(D65,Product_Reference!$A$1:$F$26,2,0),"Not Found!!") -> Router AX1800 | U65: =IFERROR(VLOOKUP(D65,Product_Reference!$A$1:$F$26,3,0),"Not Found!!") -> Networking | V65: =IFERROR(VLOOKUP(D65,Product_Reference!$A$1:$F$26,4,0),"Not Found!!") -> NetLink | W65: =IFERROR(VLOOKUP(D65,Product_Reference!$A$1:$F$26,5,0),"Not Found!!") -> ABC Ltd | X65: =IFERROR(VLOOKUP(D65,Product_Reference!$A$1:$F$26,6,0),"Not Found!!") -> 4.5
A66: ORD1065 | B66: 46026 | C66: C016 | D66: P101 | E66: 4 | F66: 45000 | G66: 0.12 | H66: UPI | I66: North | J66: Priya | K66: =PRODUCT(E66,F66) -> 180000 | L66: =PRODUCT(K66,G66) -> 21600 | M66: =K66-L66 -> 158400 | N66: =IF(M66>=50000,"High Value",IF(M66>=20000,"Medium Value","Low Value")) -> High Value | O66: =IF(AND(E66>=5,G66>=15%),"High",IF(OR(E66>=3,G66>=10%),"Medium","Low")) -> Medium | P66: =RIGHT(C66,3) -> 016 | Q66: =RIGHT(D66,3) -> 101 | R66: =PROPER(TRIM(J66)) -> Priya | S66: =TRIM(PROPER(I66)) -> North | T66: =IFERROR(VLOOKUP(D66,Product_Reference!$A$1:$F$26,2,0),"Not Found!!") -> Laptop Pro 14 | U66: =IFERROR(VLOOKUP(D66,Product_Reference!$A$1:$F$26,3,0),"Not Found!!") -> Electronics | V66: =IFERROR(VLOOKUP(D66,Product_Reference!$A$1:$F$26,4,0),"Not Found!!") -> TechPro | W66: =IFERROR(VLOOKUP(D66,Product_Reference!$A$1:$F$26,5,0),"Not Found!!") -> ABC Ltd | X66: =IFERROR(VLOOKUP(D66,Product_Reference!$A$1:$F$26,6,0),"Not Found!!") -> 4.5
A67: ORD1066 | B67: 46034 | C67: C050 | D67: P117 | E67: 2 | F67: 1800 | G67: 0.2 | H67: Card | I67: East | J67: Rahul | K67: =PRODUCT(E67,F67) -> 3600 | L67: =PRODUCT(K67,G67) -> 720 | M67: =K67-L67 -> 2880 | N67: =IF(M67>=50000,"High Value",IF(M67>=20000,"Medium Value","Low Value")) -> Low Value | O67: =IF(AND(E67>=5,G67>=15%),"High",IF(OR(E67>=3,G67>=10%),"Medium","Low")) -> Medium | P67: =RIGHT(C67,3) -> 050 | Q67: =RIGHT(D67,3) -> 117 | R67: =PROPER(TRIM(J67)) -> Rahul | S67: =TRIM(PROPER(I67)) -> East | T67: =IFERROR(VLOOKUP(D67,Product_Reference!$A$1:$F$26,2,0),"Not Found!!") -> Laptop Stand | U67: =IFERROR(VLOOKUP(D67,Product_Reference!$A$1:$F$26,3,0),"Not Found!!") -> Accessories | V67: =IFERROR(VLOOKUP(D67,Product_Reference!$A$1:$F$26,4,0),"Not Found!!") -> ErgoTech | W67: =IFERROR(VLOOKUP(D67,Product_Reference!$A$1:$F$26,5,0),"Not Found!!") -> PQR Ltd | X67: =IFERROR(VLOOKUP(D67,Product_Reference!$A$1:$F$26,6,0),"Not Found!!") -> 4
A68: ORD1067 | B68: 46089 | C68: C001 | D68: P119 | E68: 2 | F68: 12500 | G68: 0.1 | H68: Net Banking | I68: West | J68: Amit | K68: =PRODUCT(E68,F68) -> 25000 | L68: =PRODUCT(K68,G68) -> 2500 | M68: =K68-L68 -> 22500 | N68: =IF(M68>=50000,"High Value",IF(M68>=20000,"Medium Value","Low Value")) -> Medium Value | O68: =IF(AND(E68>=5,G68>=15%),"High",IF(OR(E68>=3,G68>=10%),"Medium","Low")) -> Medium | P68: =RIGHT(C68,3) -> 001 | Q68: =RIGHT(D68,3) -> 119 | R68: =PROPER(TRIM(J68)) -> Amit | S68: =TRIM(PROPER(I68)) -> West | T68: =IFERROR(VLOOKUP(D68,Product_Reference!$A$1:$F$26,2,0),"Not Found!!") -> Office Chair | U68: =IFERROR(VLOOKUP(D68,Product_Reference!$A$1:$F$26,3,0),"Not Found!!") -> Furniture | V68: =IFERROR(VLOOKUP(D68,Product_Reference!$A$1:$F$26,4,0),"Not Found!!") -> ComfortPro | W68: =IFERROR(VLOOKUP(D68,Product_Reference!$A$1:$F$26,5,0),"Not Found!!") -> ABC Ltd | X68: =IFERROR(VLOOKUP(D68,Product_Reference!$A$1:$F$26,6,0),"Not Found!!") -> 4.2
A69: ORD1068 | B69: 46057 | C69: C023 | D69: P112 | E69: 1 | F69: 3200 | G69: 0.12 | H69: UPI | I69: South | J69: Rahul | K69: =PRODUCT(E69,F69) -> 3200 | L69: =PRODUCT(K69,G69) -> 384 | M69: =K69-L69 -> 2816 | N69: =IF(M69>=50000,"High Value",IF(M69>=20000,"Medium Value","Low Value")) -> Low Value | O69: =IF(AND(E69>=5,G69>=15%),"High",IF(OR(E69>=3,G69>=10%),"Medium","Low")) -> Medium | P69: =RIGHT(C69,3) -> 023 | Q69: =RIGHT(D69,3) -> 112 | R69: =PROPER(TRIM(J69)) -> Rahul | S69: =TRIM(PROPER(I69)) -> South | T69: =IFERROR(VLOOKUP(D69,Product_Reference!$A$1:$F$26,2,0),"Not Found!!") -> Webcam HD | U69: =IFERROR(VLOOKUP(D69,Product_Reference!$A$1:$F$26,3,0),"Not Found!!") -> Accessories | V69: =IFERROR(VLOOKUP(D69,Product_Reference!$A$1:$F$26,4,0),"Not Found!!") -> VisionTech | W69: =IFERROR(VLOOKUP(D69,Product_Reference!$A$1:$F$26,5,0),"Not Found!!") -> ABC Ltd | X69: =IFERROR(VLOOKUP(D69,Product_Reference!$A$1:$F$26,6,0),"Not Found!!") -> 3.8
A70: ORD1069 | B70: 46056 | C70: C051 | D70: P110 | E70: 6 | F70: 9000 | G70: 0.15 | H70: UPI | I70: South | J70: Priya | K70: =PRODUCT(E70,F70) -> 54000 | L70: =PRODUCT(K70,G70) -> 8100 | M70: =K70-L70 -> 45900 | N70: =IF(M70>=50000,"High Value",IF(M70>=20000,"Medium Value","Low Value")) -> Medium Value | O70: =IF(AND(E70>=5,G70>=15%),"High",IF(OR(E70>=3,G70>=10%),"Medium","Low")) -> High | P70: =RIGHT(C70,3) -> 051 | Q70: =RIGHT(D70,3) -> 110 | R70: =PROPER(TRIM(J70)) -> Priya | S70: =TRIM(PROPER(I70)) -> South | T70: =IFERROR(VLOOKUP(D70,Product_Reference!$A$1:$F$26,2,0),"Not Found!!") -> External SSD 1TB | U70: =IFERROR(VLOOKUP(D70,Product_Reference!$A$1:$F$26,3,0),"Not Found!!") -> Storage | V70: =IFERROR(VLOOKUP(D70,Product_Reference!$A$1:$F$26,4,0),"Not Found!!") -> DataDrive | W70: =IFERROR(VLOOKUP(D70,Product_Reference!$A$1:$F$26,5,0),"Not Found!!") -> PQR Ltd | X70: =IFERROR(VLOOKUP(D70,Product_Reference!$A$1:$F$26,6,0),"Not Found!!") -> 4.5
A71: ORD1070 | B71: 46097 | C71: C029 | D71: P121 | E71: 1 | F71: 30000 | G71: 0.12 | H71: UPI | I71: East | J71: Karan | K71: =PRODUCT(E71,F71) -> 30000 | L71: =PRODUCT(K71,G71) -> 3600 | M71: =K71-L71 -> 26400 | N71: =IF(M71>=50000,"High Value",IF(M71>=20000,"Medium Value","Low Value")) -> Medium Value | O71: =IF(AND(E71>=5,G71>=15%),"High",IF(OR(E71>=3,G71>=10%),"Medium","Low")) -> Medium | P71: =RIGHT(C71,3) -> 029 | Q71: =RIGHT(D71,3) -> 121 | R71: =PROPER(TRIM(J71)) -> Karan | S71: =TRIM(PROPER(I71)) -> East | T71: =IFERROR(VLOOKUP(D71,Product_Reference!$A$1:$F$26,2,0),"Not Found!!") -> Portable Projector | U71: =IFERROR(VLOOKUP(D71,Product_Reference!$A$1:$F$26,3,0),"Not Found!!") -> Electronics | V71: =IFERROR(VLOOKUP(D71,Product_Reference!$A$1:$F$26,4,0),"Not Found!!") -> ViewMax | W71: =IFERROR(VLOOKUP(D71,Product_Reference!$A$1:$F$26,5,0),"Not Found!!") -> PQR Ltd | X71: =IFERROR(VLOOKUP(D71,Product_Reference!$A$1:$F$26,6,0),"Not Found!!") -> 4.1
... A92: ORD1091 | B92: 46080 | C92: C060 | D92: P104 | E92: 6 | F92: 28000 | G92: 0.2 | H92: Card | I92: South | J92: Karan | K92: =PRODUCT(E92,F92) -> 168000 | L92: =PRODUCT(K92,G92) -> 33600 | M92: =K92-L92 -> 134400 | N92: =IF(M92>=50000,"High Value",IF(M92>=20000,"Medium Value","Low Value")) -> High Value | O92: =IF(AND(E92>=5,G92>=15%),"High",IF(OR(E92>=3,G92>=10%),"Medium","Low")) -> High | P92: =RIGHT(C92,3) -> 060 | Q92: =RIGHT(D92,3) -> 104 | R92: =PROPER(TRIM(J92)) -> Karan | S92: =TRIM(PROPER(I92)) -> South | T92: =IFERROR(VLOOKUP(D92,Product_Reference!$A$1:$F$26,2,0),"Not Found!!") -> Tablet 10 | U92: =IFERROR(VLOOKUP(D92,Product_Reference!$A$1:$F$26,3,0),"Not Found!!") -> Electronics | V92: =IFERROR(VLOOKUP(D92,Product_Reference!$A$1:$F$26,4,0),"Not Found!!") -> TabWorld | W92: =IFERROR(VLOOKUP(D92,Product_Reference!$A$1:$F$26,5,0),"Not Found!!") -> PQR Ltd | X92: =IFERROR(VLOOKUP(D92,Product_Reference!$A$1:$F$26,6,0),"Not Found!!") -> 4.1
A93: ORD1092 | B93: 46049 | C93: C054 | D93: P109 | E93: 2 | F93: 8500 | G93: 0.2 | I93: East | J93: Rahul | K93: =PRODUCT(E93,F93) -> 17000 | L93: =PRODUCT(K93,G93) -> 3400 | M93: =K93-L93 -> 13600 | N93: =IF(M93>=50000,"High Value",IF(M93>=20000,"Medium Value","Low Value")) -> Low Value | O93: =IF(AND(E93>=5,G93>=15%),"High",IF(OR(E93>=3,G93>=10%),"Medium","Low")) -> Medium | P93: =RIGHT(C93,3) -> 054 | Q93: =RIGHT(D93,3) -> 109 | R93: =PROPER(TRIM(J93)) -> Rahul | S93: =TRIM(PROPER(I93)) -> East | T93: =IFERROR(VLOOKUP(D93,Product_Reference!$A$1:$F$26,2,0),"Not Found!!") -> Noise Cancelling Headphones | U93: =IFERROR(VLOOKUP(D93,Product_Reference!$A$1:$F$26,3,0),"Not Found!!") -> Audio | V93: =IFERROR(VLOOKUP(D93,Product_Reference!$A$1:$F$26,4,0),"Not Found!!") -> SoundMax | W93: =IFERROR(VLOOKUP(D93,Product_Reference!$A$1:$F$26,5,0),"Not Found!!") -> LMN Ltd | X93: =IFERROR(VLOOKUP(D93,Product_Reference!$A$1:$F$26,6,0),"Not Found!!") -> 4.7
A94: ORD1093 | B94: 46051 | C94: C013 | D94: P121 | E94: 2 | F94: 30000 | G94: 0.12 | H94: Net Banking | I94: East | J94: Neha | K94: =PRODUCT(E94,F94) -> 60000 | L94: =PRODUCT(K94,G94) -> 7200 | M94: =K94-L94 -> 52800 | N94: =IF(M94>=50000,"High Value",IF(M94>=20000,"Medium Value","Low Value")) -> High Value | O94: =IF(AND(E94>=5,G94>=15%),"High",IF(OR(E94>=3,G94>=10%),"Medium","Low")) -> Medium | P94: =RIGHT(C94,3) -> 013 | Q94: =RIGHT(D94,3) -> 121 | R94: =PROPER(TRIM(J94)) -> Neha | S94: =TRIM(PROPER(I94)) -> East | T94: =IFERROR(VLOOKUP(D94,Product_Reference!$A$1:$F$26,2,0),"Not Found!!") -> Portable Projector | U94: =IFERROR(VLOOKUP(D94,Product_Reference!$A$1:$F$26,3,0),"Not Found!!") -> Electronics | V94: =IFERROR(VLOOKUP(D94,Product_Reference!$A$1:$F$26,4,0),"Not Found!!") -> ViewMax | W94: =IFERROR(VLOOKUP(D94,Product_Reference!$A$1:$F$26,5,0),"Not Found!!") -> PQR Ltd | X94: =IFERROR(VLOOKUP(D94,Product_Reference!$A$1:$F$26,6,0),"Not Found!!") -> 4.1
A95: ORD1094 | B95: 46091 | C95: C047 | D95: P118 | E95: 1 | F95: 650 | G95: 0.2 | H95: Net Banking | I95: West | J95: Neha | K95: =PRODUCT(E95,F95) -> 650 | L95: =PRODUCT(K95,G95) -> 130 | M95: =K95-L95 -> 520 | N95: =IF(M95>=50000,"High Value",IF(M95>=20000,"Medium Value","Low Value")) -> Low Value | O95: =IF(AND(E95>=5,G95>=15%),"High",IF(OR(E95>=3,G95>=10%),"Medium","Low")) -> Medium | P95: =RIGHT(C95,3) -> 047 | Q95: =RIGHT(D95,3) -> 118 | R95: =PROPER(TRIM(J95)) -> Neha | S95: =TRIM(PROPER(I95)) -> West | T95: =IFERROR(VLOOKUP(D95,Product_Reference!$A$1:$F$26,2,0),"Not Found!!") -> Mechanical Pencil Set | U95: =IFERROR(VLOOKUP(D95,Product_Reference!$A$1:$F$26,3,0),"Not Found!!") -> Stationery | V95: =IFERROR(VLOOKUP(D95,Product_Reference!$A$1:$F$26,4,0),"Not Found!!") -> WriteWell | W95: =IFERROR(VLOOKUP(D95,Product_Reference!$A$1:$F$26,5,0),"Not Found!!") -> LMN Ltd | X95: =IFERROR(VLOOKUP(D95,Product_Reference!$A$1:$F$26,6,0),"Not Found!!") -> 4.3
A96: ORD1095 | B96: 46055 | C96: C054 | D96: P118 | E96: 2 | F96: 650 | G96: 0.18 | H96: Cash | I96: South | J96: Rahul | K96: =PRODUCT(E96,F96) -> 1300 | L96: =PRODUCT(K96,G96) -> 234 | M96: =K96-L96 -> 1066 | N96: =IF(M96>=50000,"High Value",IF(M96>=20000,"Medium Value","Low Value")) -> Low Value | O96: =IF(AND(E96>=5,G96>=15%),"High",IF(OR(E96>=3,G96>=10%),"Medium","Low")) -> Medium | P96: =RIGHT(C96,3) -> 054 | Q96: =RIGHT(D96,3) -> 118 | R96: =PROPER(TRIM(J96)) -> Rahul | S96: =TRIM(PROPER(I96)) -> South | T96: =IFERROR(VLOOKUP(D96,Product_Reference!$A$1:$F$26,2,0),"Not Found!!") -> Mechanical Pencil Set | U96: =IFERROR(VLOOKUP(D96,Product_Reference!$A$1:$F$26,3,0),"Not Found!!") -> Stationery | V96: =IFERROR(VLOOKUP(D96,Product_Reference!$A$1:$F$26,4,0),"Not Found!!") -> WriteWell | W96: =IFERROR(VLOOKUP(D96,Product_Reference!$A$1:$F$26,5,0),"Not Found!!") -> LMN Ltd | X96: =IFERROR(VLOOKUP(D96,Product_Reference!$A$1:$F$26,6,0),"Not Found!!") -> 4.3
A97: ORD1096 | B97: 46085 | C97: C025 | D97: P111 | E97: 2 | F97: 18000 | G97: 0.05 | H97: Net Banking | I97: North | J97: Rahul | K97: =PRODUCT(E97,F97) -> 36000 | L97: =PRODUCT(K97,G97) -> 1800 | M97: =K97-L97 -> 34200 | N97: =IF(M97>=50000,"High Value",IF(M97>=20000,"Medium Value","Low Value")) -> Medium Value | O97: =IF(AND(E97>=5,G97>=15%),"High",IF(OR(E97>=3,G97>=10%),"Medium","Low")) -> Low | P97: =RIGHT(C97,3) -> 025 | Q97: =RIGHT(D97,3) -> 111 | R97: =PROPER(TRIM(J97)) -> Rahul | S97: =TRIM(PROPER(I97)) -> North | T97: =IFERROR(VLOOKUP(D97,Product_Reference!$A$1:$F$26,2,0),"Not Found!!") -> Gaming Monitor 24 | U97: =IFERROR(VLOOKUP(D97,Product_Reference!$A$1:$F$26,3,0),"Not Found!!") -> Electronics | V97: =IFERROR(VLOOKUP(D97,Product_Reference!$A$1:$F$26,4,0),"Not Found!!") -> ViewMax | W97: =IFERROR(VLOOKUP(D97,Product_Reference!$A$1:$F$26,5,0),"Not Found!!") -> XYZ Ltd | X97: =IFERROR(VLOOKUP(D97,Product_Reference!$A$1:$F$26,6,0),"Not Found!!") -> 4.2
A98: ORD1097 | B98: 46023 | C98: C021 | D98: P113 | E98: 1 | F98: 5500 | G98: 0.05 | H98: UPI | I98: West | J98: Sneha | K98: =PRODUCT(E98,F98) -> 5500 | L98: =PRODUCT(K98,G98) -> 275 | M98: =K98-L98 -> 5225 | N98: =IF(M98>=50000,"High Value",IF(M98>=20000,"Medium Value","Low Value")) -> Low Value | O98: =IF(AND(E98>=5,G98>=15%),"High",IF(OR(E98>=3,G98>=10%),"Medium","Low")) -> Low | P98: =RIGHT(C98,3) -> 021 | Q98: =RIGHT(D98,3) -> 113 | R98: =PROPER(TRIM(J98)) -> Sneha | S98: =TRIM(PROPER(I98)) -> West | T98: =IFERROR(VLOOKUP(D98,Product_Reference!$A$1:$F$26,2,0),"Not Found!!") -> Wireless Earbuds | U98: =IFERROR(VLOOKUP(D98,Product_Reference!$A$1:$F$26,3,0),"Not Found!!") -> Audio | V98: =IFERROR(VLOOKUP(D98,Product_Reference!$A$1:$F$26,4,0),"Not Found!!") -> SoundMax | W98: =IFERROR(VLOOKUP(D98,Product_Reference!$A$1:$F$26,5,0),"Not Found!!") -> LMN Ltd | X98: =IFERROR(VLOOKUP(D98,Product_Reference!$A$1:$F$26,6,0),"Not Found!!") -> 4.4
A99: ORD1098 | B99: 46027 | C99: C038 | D99: P117 | E99: 2 | F99: 1800 | G99: 0.18 | H99: Net Banking | I99: North | J99: AMIT | K99: =PRODUCT(E99,F99) -> 3600 | L99: =PRODUCT(K99,G99) -> 648 | M99: =K99-L99 -> 2952 | N99: =IF(M99>=50000,"High Value",IF(M99>=20000,"Medium Value","Low Value")) -> Low Value | O99: =IF(AND(E99>=5,G99>=15%),"High",IF(OR(E99>=3,G99>=10%),"Medium","Low")) -> Medium | P99: =RIGHT(C99,3) -> 038 | Q99: =RIGHT(D99,3) -> 117 | R99: =PROPER(TRIM(J99)) -> Amit | S99: =TRIM(PROPER(I99)) -> North | T99: =IFERROR(VLOOKUP(D99,Product_Reference!$A$1:$F$26,2,0),"Not Found!!") -> Laptop Stand | U99: =IFERROR(VLOOKUP(D99,Product_Reference!$A$1:$F$26,3,0),"Not Found!!") -> Accessories | V99: =IFERROR(VLOOKUP(D99,Product_Reference!$A$1:$F$26,4,0),"Not Found!!") -> ErgoTech | W99: =IFERROR(VLOOKUP(D99,Product_Reference!$A$1:$F$26,5,0),"Not Found!!") -> PQR Ltd | X99: =IFERROR(VLOOKUP(D99,Product_Reference!$A$1:$F$26,6,0),"Not Found!!") -> 4
A100: ORD1099 | B100: 46096 | C100: C019 | D100: P121 | E100: 2 | F100: 30000 | G100: 0.05 | H100: UPI | I100: West | J100: Rahul | K100: =PRODUCT(E100,F100) -> 60000 | L100: =PRODUCT(K100,G100) -> 3000 | M100: =K100-L100 -> 57000 | N100: =IF(M100>=50000,"High Value",IF(M100>=20000,"Medium Value","Low Value")) -> High Value | O100: =IF(AND(E100>=5,G100>=15%),"High",IF(OR(E100>=3,G100>=10%),"Medium","Low")) -> Low | P100: =RIGHT(C100,3) -> 019 | Q100: =RIGHT(D100,3) -> 121 | R100: =PROPER(TRIM(J100)) -> Rahul | S100: =TRIM(PROPER(I100)) -> West | T100: =IFERROR(VLOOKUP(D100,Product_Reference!$A$1:$F$26,2,0),"Not Found!!") -> Portable Projector | U100: =IFERROR(VLOOKUP(D100,Product_Reference!$A$1:$F$26,3,0),"Not Found!!") -> Electronics | V100: =IFERROR(VLOOKUP(D100,Product_Reference!$A$1:$F$26,4,0),"Not Found!!") -> ViewMax | W100: =IFERROR(VLOOKUP(D100,Product_Reference!$A$1:$F$26,5,0),"Not Found!!") -> PQR Ltd | X100: =IFERROR(VLOOKUP(D100,Product_Reference!$A$1:$F$26,6,0),"Not Found!!") -> 4.1
A101: ORD1100 | B101: 46067 | C101: C013 | D101: P114 | E101: 1 | F101: 2500 | G101: 0.08 | H101: UPI | I101: East | J101: Rahul | K101: =PRODUCT(E101,F101) -> 2500 | L101: =PRODUCT(K101,G101) -> 200 | M101: =K101-L101 -> 2300 | N101: =IF(M101>=50000,"High Value",IF(M101>=20000,"Medium Value","Low Value")) -> Low Value | O101: =IF(AND(E101>=5,G101>=15%),"High",IF(OR(E101>=3,G101>=10%),"Medium","Low")) -> Low | P101: =RIGHT(C101,3) -> 013 | Q101: =RIGHT(D101,3) -> 114 | R101: =PROPER(TRIM(J101)) -> Rahul | S101: =TRIM(PROPER(I101)) -> East | T101: =IFERROR(VLOOKUP(D101,Product_Reference!$A$1:$F$26,2,0),"Not Found!!") -> Power Bank 20000mAh | U101: =IFERROR(VLOOKUP(D101,Product_Reference!$A$1:$F$26,3,0),"Not Found!!") -> Accessories | V101: =IFERROR(VLOOKUP(D101,Product_Reference!$A$1:$F$26,4,0),"Not Found!!") -> PowerPlus | W101: =IFERROR(VLOOKUP(D101,Product_Reference!$A$1:$F$26,5,0),"Not Found!!") -> PQR Ltd | X101: =IFERROR(VLOOKUP(D101,Product_Reference!$A$1:$F$26,6,0),"Not Found!!") -> 4.1
A102: ORD1101 | B102: 46094 | C102: C039 | D102: P108 | E102: 1 | F102: 7000 | G102: 0.1 | H102: Card | I102: West | J102: Neha | K102: =PRODUCT(E102,F102) -> 7000 | L102: =PRODUCT(K102,G102) -> 700 | M102: =K102-L102 -> 6300 | N102: =IF(M102>=50000,"High Value",IF(M102>=20000,"Medium Value","Low Value")) -> Low Value | O102: =IF(AND(E102>=5,G102>=15%),"High",IF(OR(E102>=3,G102>=10%),"Medium","Low")) -> Medium | P102: =RIGHT(C102,3) -> 039 | Q102: =RIGHT(D102,3) -> 108 | R102: =PROPER(TRIM(J102)) -> Neha | S102: =TRIM(PROPER(I102)) -> West | T102: =IFERROR(VLOOKUP(D102,Product_Reference!$A$1:$F$26,2,0),"Not Found!!") -> Smart Watch | U102: =IFERROR(VLOOKUP(D102,Product_Reference!$A$1:$F$26,3,0),"Not Found!!") -> Wearables | V102: =IFERROR(VLOOKUP(D102,Product_Reference!$A$1:$F$26,4,0),"Not Found!!") -> FitTech | W102: =IFERROR(VLOOKUP(D102,Product_Reference!$A$1:$F$26,5,0),"Not Found!!") -> ABC Ltd | X102: =IFERROR(VLOOKUP(D102,Product_Reference!$A$1:$F$26,6,0),"Not Found!!") -> 4
A103: ORD1102 | B103: 46072 | C103: C012 | D103: P122 | E103: 1 | F103: 5500 | G103: 0.08 | H103: Cash | I103: South | J103: Karan | K103: =PRODUCT(E103,F103) -> 5500 | L103: =PRODUCT(K103,G103) -> 440 | M103: =K103-L103 -> 5060 | N103: =IF(M103>=50000,"High Value",IF(M103>=20000,"Medium Value","Low Value")) -> Low Value | O103: =IF(AND(E103>=5,G103>=15%),"High",IF(OR(E103>=3,G103>=10%),"Medium","Low")) -> Low | P103: =RIGHT(C103,3) -> 012 | Q103: =RIGHT(D103,3) -> 122 | R103: =PROPER(TRIM(J103)) -> Karan | S103: =TRIM(PROPER(I103)) -> South | T103: =IFERROR(VLOOKUP(D103,Product_Reference!$A$1:$F$26,2,0),"Not Found!!") -> Router AX1800 | U103: =IFERROR(VLOOKUP(D103,Product_Reference!$A$1:$F$26,3,0),"Not Found!!") -> Networking | V103: =IFERROR(VLOOKUP(D103,Product_Reference!$A$1:$F$26,4,0),"Not Found!!") -> NetLink | W103: =IFERROR(VLOOKUP(D103,Product_Reference!$A$1:$F$26,5,0),"Not Found!!") -> ABC Ltd | X103: =IFERROR(VLOOKUP(D103,Product_Reference!$A$1:$F$26,6,0),"Not Found!!") -> 4.5
A104: ORD1103 | B104: 46069 | C104: C023 | D104: P125 | E104: 1 | F104: 16000 | G104: 0.2 | H104: Cash | I104: East | J104: Neha | K104: =PRODUCT(E104,F104) -> 16000 | L104: =PRODUCT(K104,G104) -> 3200 | M104: =K104-L104 -> 12800 | N104: =IF(M104>=50000,"High Value",IF(M104>=20000,"Medium Value","Low Value")) -> Low Value | O104: =IF(AND(E104>=5,G104>=15%),"High",IF(OR(E104>=3,G104>=10%),"Medium","Low")) -> Medium | P104: =RIGHT(C104,3) -> 023 | Q104: =RIGHT(D104,3) -> 125 | R104: =PROPER(TRIM(J104)) -> Neha | S104: =TRIM(PROPER(I104)) -> East | T104: =IFERROR(VLOOKUP(D104,Product_Reference!$A$1:$F$26,2,0),"Not Found!!") -> Laser Printer | U104: =IFERROR(VLOOKUP(D104,Product_Reference!$A$1:$F$26,3,0),"Not Found!!") -> Office Equipment | V104: =IFERROR(VLOOKUP(D104,Product_Reference!$A$1:$F$26,4,0),"Not Found!!") -> PrintPro | W104: =IFERROR(VLOOKUP(D104,Product_Reference!$A$1:$F$26,5,0),"Not Found!!") -> ABC Ltd | X104: =IFERROR(VLOOKUP(D104,Product_Reference!$A$1:$F$26,6,0),"Not Found!!") -> 4.2
A105: ORD1104 | B105: 46060 | C105: C060 | D105: P102 | E105: 1 | F105: 1200 | G105: 0.18 | H105: Net Banking | I105: West | J105: Priya | K105: =PRODUCT(E105,F105) -> 1200 | L105: =PRODUCT(K105,G105) -> 216 | M105: =K105-L105 -> 984 | N105: =IF(M105>=50000,"High Value",IF(M105>=20000,"Medium Value","Low Value")) -> Low Value | O105: =IF(AND(E105>=5,G105>=15%),"High",IF(OR(E105>=3,G105>=10%),"Medium","Low")) -> Medium | P105: =RIGHT(C105,3) -> 060 | Q105: =RIGHT(D105,3) -> 102 | R105: =PROPER(TRIM(J105)) -> Priya | S105: =TRIM(PROPER(I105)) -> West | T105: =IFERROR(VLOOKUP(D105,Product_Reference!$A$1:$F$26,2,0),"Not Found!!") -> Wireless Mouse | U105: =IFERROR(VLOOKUP(D105,Product_Reference!$A$1:$F$26,3,0),"Not Found!!") -> Accessories | V105: =IFERROR(VLOOKUP(D105,Product_Reference!$A$1:$F$26,4,0),"Not Found!!") -> ClickTech | W105: =IFERROR(VLOOKUP(D105,Product_Reference!$A$1:$F$26,5,0),"Not Found!!") -> XYZ Ltd | X105: =IFERROR(VLOOKUP(D105,Product_Reference!$A$1:$F$26,6,0),"Not Found!!") -> 4.2
... A135: ORD1134 | B135: 46044 | C135: C060 | D135: P101 | E135: 4 | F135: 45000 | G135: 0.2 | H135: Net Banking | I135: South | J135: Amit | K135: =PRODUCT(E135,F135) -> 180000 | L135: =PRODUCT(K135,G135) -> 36000 | M135: =K135-L135 -> 144000 | N135: =IF(M135>=50000,"High Value",IF(M135>=20000,"Medium Value","Low Value")) -> High Value | O135: =IF(AND(E135>=5,G135>=15%),"High",IF(OR(E135>=3,G135>=10%),"Medium","Low")) -> Medium | P135: =RIGHT(C135,3) -> 060 | Q135: =RIGHT(D135,3) -> 101 | R135: =PROPER(TRIM(J135)) -> Amit | S135: =TRIM(PROPER(I135)) -> South | T135: =IFERROR(VLOOKUP(D135,Product_Reference!$A$1:$F$26,2,0),"Not Found!!") -> Laptop Pro 14 | U135: =IFERROR(VLOOKUP(D135,Product_Reference!$A$1:$F$26,3,0),"Not Found!!") -> Electronics | V135: =IFERROR(VLOOKUP(D135,Product_Reference!$A$1:$F$26,4,0),"Not Found!!") -> TechPro | W135: =IFERROR(VLOOKUP(D135,Product_Reference!$A$1:$F$26,5,0),"Not Found!!") -> ABC Ltd | X135: =IFERROR(VLOOKUP(D135,Product_Reference!$A$1:$F$26,6,0),"Not Found!!") -> 4.5
A136: ORD1135 | B136: 46082 | C136: C030 | D136: P109 | E136: 2 | F136: 8500 | G136: 0.15 | H136: Cash | I136: East | K136: =PRODUCT(E136,F136) -> 17000 | L136: =PRODUCT(K136,G136) -> 2550 | M136: =K136-L136 -> 14450 | N136: =IF(M136>=50000,"High Value",IF(M136>=20000,"Medium Value","Low Value")) -> Low Value | O136: =IF(AND(E136>=5,G136>=15%),"High",IF(OR(E136>=3,G136>=10%),"Medium","Low")) -> Medium | P136: =RIGHT(C136,3) -> 030 | Q136: =RIGHT(D136,3) -> 109 | R136: =PROPER(TRIM(J136)) | S136: =TRIM(PROPER(I136)) -> East | T136: =IFERROR(VLOOKUP(D136,Product_Reference!$A$1:$F$26,2,0),"Not Found!!") -> Noise Cancelling Headphones | U136: =IFERROR(VLOOKUP(D136,Product_Reference!$A$1:$F$26,3,0),"Not Found!!") -> Audio | V136: =IFERROR(VLOOKUP(D136,Product_Reference!$A$1:$F$26,4,0),"Not Found!!") -> SoundMax | W136: =IFERROR(VLOOKUP(D136,Product_Reference!$A$1:$F$26,5,0),"Not Found!!") -> LMN Ltd | X136: =IFERROR(VLOOKUP(D136,Product_Reference!$A$1:$F$26,6,0),"Not Found!!") -> 4.7
A137: ORD1136 | B137: 46026 | C137: C025 | D137: P119 | E137: 6 | F137: 12500 | G137: 0.15 | H137: Net Banking | I137: East | J137: Priya | K137: =PRODUCT(E137,F137) -> 75000 | L137: =PRODUCT(K137,G137) -> 11250 | M137: =K137-L137 -> 63750 | N137: =IF(M137>=50000,"High Value",IF(M137>=20000,"Medium Value","Low Value")) -> High Value | O137: =IF(AND(E137>=5,G137>=15%),"High",IF(OR(E137>=3,G137>=10%),"Medium","Low")) -> High | P137: =RIGHT(C137,3) -> 025 | Q137: =RIGHT(D137,3) -> 119 | R137: =PROPER(TRIM(J137)) -> Priya | S137: =TRIM(PROPER(I137)) -> East | T137: =IFERROR(VLOOKUP(D137,Product_Reference!$A$1:$F$26,2,0),"Not Found!!") -> Office Chair | U137: =IFERROR(VLOOKUP(D137,Product_Reference!$A$1:$F$26,3,0),"Not Found!!") -> Furniture | V137: =IFERROR(VLOOKUP(D137,Product_Reference!$A$1:$F$26,4,0),"Not Found!!") -> ComfortPro | W137: =IFERROR(VLOOKUP(D137,Product_Reference!$A$1:$F$26,5,0),"Not Found!!") -> ABC Ltd | X137: =IFERROR(VLOOKUP(D137,Product_Reference!$A$1:$F$26,6,0),"Not Found!!") -> 4.2
A138: ORD1137 | B138: 46036 | C138: C032 | D138: P108 | E138: 4 | F138: 7000 | G138: 0.18 | H138: Card | I138: West | J138: Rahul | K138: =PRODUCT(E138,F138) -> 28000 | L138: =PRODUCT(K138,G138) -> 5040 | M138: =K138-L138 -> 22960 | N138: =IF(M138>=50000,"High Value",IF(M138>=20000,"Medium Value","Low Value")) -> Medium Value | O138: =IF(AND(E138>=5,G138>=15%),"High",IF(OR(E138>=3,G138>=10%),"Medium","Low")) -> Medium | P138: =RIGHT(C138,3) -> 032 | Q138: =RIGHT(D138,3) -> 108 | R138: =PROPER(TRIM(J138)) -> Rahul | S138: =TRIM(PROPER(I138)) -> West | T138: =IFERROR(VLOOKUP(D138,Product_Reference!$A$1:$F$26,2,0),"Not Found!!") -> Smart Watch | U138: =IFERROR(VLOOKUP(D138,Product_Reference!$A$1:$F$26,3,0),"Not Found!!") -> Wearables | V138: =IFERROR(VLOOKUP(D138,Product_Reference!$A$1:$F$26,4,0),"Not Found!!") -> FitTech | W138: =IFERROR(VLOOKUP(D138,Product_Reference!$A$1:$F$26,5,0),"Not Found!!") -> ABC Ltd | X138: =IFERROR(VLOOKUP(D138,Product_Reference!$A$1:$F$26,6,0),"Not Found!!") -> 4
A139: ORD1138 | B139: 46039 | C139: C033 | D139: P123 | E139: 1 | F139: 2800 | G139: 0 | H139: UPI | I139: West | J139: Neha | K139: =PRODUCT(E139,F139) -> 2800 | L139: =PRODUCT(K139,G139) -> 0 | M139: =K139-L139 -> 2800 | N139: =IF(M139>=50000,"High Value",IF(M139>=20000,"Medium Value","Low Value")) -> Low Value | O139: =IF(AND(E139>=5,G139>=15%),"High",IF(OR(E139>=3,G139>=10%),"Medium","Low")) -> Low | P139: =RIGHT(C139,3) -> 033 | Q139: =RIGHT(D139,3) -> 123 | R139: =PROPER(TRIM(J139)) -> Neha | S139: =TRIM(PROPER(I139)) -> West | T139: =IFERROR(VLOOKUP(D139,Product_Reference!$A$1:$F$26,2,0),"Not Found!!") -> Wi-Fi Range Extender | U139: =IFERROR(VLOOKUP(D139,Product_Reference!$A$1:$F$26,3,0),"Not Found!!") -> Networking | V139: =IFERROR(VLOOKUP(D139,Product_Reference!$A$1:$F$26,4,0),"Not Found!!") -> NetLink | W139: =IFERROR(VLOOKUP(D139,Product_Reference!$A$1:$F$26,5,0),"Not Found!!") -> XYZ Ltd | X139: =IFERROR(VLOOKUP(D139,Product_Reference!$A$1:$F$26,6,0),"Not Found!!") -> 4
A140: ORD1139 | B140: 46073 | C140: C039 | D140: P121 | E140: 4 | F140: 30000 | G140: 0.2 | H140: UPI | I140: West | J140: Amit | K140: =PRODUCT(E140,F140) -> 120000 | L140: =PRODUCT(K140,G140) -> 24000 | M140: =K140-L140 -> 96000 | N140: =IF(M140>=50000,"High Value",IF(M140>=20000,"Medium Value","Low Value")) -> High Value | O140: =IF(AND(E140>=5,G140>=15%),"High",IF(OR(E140>=3,G140>=10%),"Medium","Low")) -> Medium | P140: =RIGHT(C140,3) -> 039 | Q140: =RIGHT(D140,3) -> 121 | R140: =PROPER(TRIM(J140)) -> Amit | S140: =TRIM(PROPER(I140)) -> West | T140: =IFERROR(VLOOKUP(D140,Product_Reference!$A$1:$F$26,2,0),"Not Found!!") -> Portable Projector | U140: =IFERROR(VLOOKUP(D140,Product_Reference!$A$1:$F$26,3,0),"Not Found!!") -> Electronics | V140: =IFERROR(VLOOKUP(D140,Product_Reference!$A$1:$F$26,4,0),"Not Found!!") -> ViewMax | W140: =IFERROR(VLOOKUP(D140,Product_Reference!$A$1:$F$26,5,0),"Not Found!!") -> PQR Ltd | X140: =IFERROR(VLOOKUP(D140,Product_Reference!$A$1:$F$26,6,0),"Not Found!!") -> 4.1
A141: ORD1140 | B141: 46064 | C141: C052 | D141: P107 | E141: 1 | F141: 2200 | G141: 0.2 | H141: Cash | I141: East | J141: Rahul | K141: =PRODUCT(E141,F141) -> 2200 | L141: =PRODUCT(K141,G141) -> 440 | M141: =K141-L141 -> 1760 | N141: =IF(M141>=50000,"High Value",IF(M141>=20000,"Medium Value","Low Value")) -> Low Value | O141: =IF(AND(E141>=5,G141>=15%),"High",IF(OR(E141>=3,G141>=10%),"Medium","Low")) -> Medium | P141: =RIGHT(C141,3) -> 052 | Q141: =RIGHT(D141,3) -> 107 | R141: =PROPER(TRIM(J141)) -> Rahul | S141: =TRIM(PROPER(I141)) -> East | T141: =IFERROR(VLOOKUP(D141,Product_Reference!$A$1:$F$26,2,0),"Not Found!!") -> USB-C Hub | U141: =IFERROR(VLOOKUP(D141,Product_Reference!$A$1:$F$26,3,0),"Not Found!!") -> Accessories | V141: =IFERROR(VLOOKUP(D141,Product_Reference!$A$1:$F$26,4,0),"Not Found!!") -> ConnectPro | W141: =IFERROR(VLOOKUP(D141,Product_Reference!$A$1:$F$26,5,0),"Not Found!!") -> PQR Ltd | X141: =IFERROR(VLOOKUP(D141,Product_Reference!$A$1:$F$26,6,0),"Not Found!!") -> 4.3
A142: ORD1141 | B142: 46058 | C142: C029 | D142: P120 | E142: 3 | F142: 2200 | G142: 0.08 | H142: UPI | I142: East | J142: Karan | K142: =PRODUCT(E142,F142) -> 6600 | L142: =PRODUCT(K142,G142) -> 528 | M142: =K142-L142 -> 6072 | N142: =IF(M142>=50000,"High Value",IF(M142>=20000,"Medium Value","Low Value")) -> Low Value | O142: =IF(AND(E142>=5,G142>=15%),"High",IF(OR(E142>=3,G142>=10%),"Medium","Low")) -> Medium | P142: =RIGHT(C142,3) -> 029 | Q142: =RIGHT(D142,3) -> 120 | R142: =PROPER(TRIM(J142)) -> Karan | S142: =TRIM(PROPER(I142)) -> East | T142: =IFERROR(VLOOKUP(D142,Product_Reference!$A$1:$F$26,2,0),"Not Found!!") -> Desk Lamp | U142: =IFERROR(VLOOKUP(D142,Product_Reference!$A$1:$F$26,3,0),"Not Found!!") -> Furniture | V142: =IFERROR(VLOOKUP(D142,Product_Reference!$A$1:$F$26,4,0),"Not Found!!") -> BrightHome | W142: =IFERROR(VLOOKUP(D142,Product_Reference!$A$1:$F$26,5,0),"Not Found!!") -> XYZ Ltd | X142: =IFERROR(VLOOKUP(D142,Product_Reference!$A$1:$F$26,6,0),"Not Found!!") -> 3.9
A143: ORD1142 | B143: 46090 | C143: C022 | D143: P105 | E143: 3 | F143: 3500 | G143: 0 | H143: Card | I143: East | J143: Amit | K143: =PRODUCT(E143,F143) -> 10500 | L143: =PRODUCT(K143,G143) -> 0 | M143: =K143-L143 -> 10500 | N143: =IF(M143>=50000,"High Value",IF(M143>=20000,"Medium Value","Low Value")) -> Low Value | O143: =IF(AND(E143>=5,G143>=15%),"High",IF(OR(E143>=3,G143>=10%),"Medium","Low")) -> Medium | P143: =RIGHT(C143,3) -> 022 | Q143: =RIGHT(D143,3) -> 105 | R143: =PROPER(TRIM(J143)) -> Amit | S143: =TRIM(PROPER(I143)) -> East | T143: =IFERROR(VLOOKUP(D143,Product_Reference!$A$1:$F$26,2,0),"Not Found!!") -> Mechanical Keyboard | U143: =IFERROR(VLOOKUP(D143,Product_Reference!$A$1:$F$26,3,0),"Not Found!!") -> Accessories | V143: =IFERROR(VLOOKUP(D143,Product_Reference!$A$1:$F$26,4,0),"Not Found!!") -> KeyMaster | W143: =IFERROR(VLOOKUP(D143,Product_Reference!$A$1:$F$26,5,0),"Not Found!!") -> XYZ Ltd | X143: =IFERROR(VLOOKUP(D143,Product_Reference!$A$1:$F$26,6,0),"Not Found!!") -> 4.4
A144: ORD1143 | B144: 46060 | C144: C013 | D144: P110 | E144: 1 | F144: 9000 | G144: 0.15 | H144: UPI | I144: South | J144: Karan | K144: =PRODUCT(E144,F144) -> 9000 | L144: =PRODUCT(K144,G144) -> 1350 | M144: =K144-L144 -> 7650 | N144: =IF(M144>=50000,"High Value",IF(M144>=20000,"Medium Value","Low Value")) -> Low Value | O144: =IF(AND(E144>=5,G144>=15%),"High",IF(OR(E144>=3,G144>=10%),"Medium","Low")) -> Medium | P144: =RIGHT(C144,3) -> 013 | Q144: =RIGHT(D144,3) -> 110 | R144: =PROPER(TRIM(J144)) -> Karan | S144: =TRIM(PROPER(I144)) -> South | T144: =IFERROR(VLOOKUP(D144,Product_Reference!$A$1:$F$26,2,0),"Not Found!!") -> External SSD 1TB | U144: =IFERROR(VLOOKUP(D144,Product_Reference!$A$1:$F$26,3,0),"Not Found!!") -> Storage | V144: =IFERROR(VLOOKUP(D144,Product_Reference!$A$1:$F$26,4,0),"Not Found!!") -> DataDrive | W144: =IFERROR(VLOOKUP(D144,Product_Reference!$A$1:$F$26,5,0),"Not Found!!") -> PQR Ltd | X144: =IFERROR(VLOOKUP(D144,Product_Reference!$A$1:$F$26,6,0),"Not Found!!") -> 4.5
A145: ORD1144 | B145: 46037 | C145: C029 | D145: P124 | E145: 2 | F145: 2500 | G145: 0.2 | H145: Card | I145: East | J145: Sneha | K145: =PRODUCT(E145,F145) -> 5000 | L145: =PRODUCT(K145,G145) -> 1000 | M145: =K145-L145 -> 4000 | N145: =IF(M145>=50000,"High Value",IF(M145>=20000,"Medium Value","Low Value")) -> Low Value | O145: =IF(AND(E145>=5,G145>=15%),"High",IF(OR(E145>=3,G145>=10%),"Medium","Low")) -> Medium | P145: =RIGHT(C145,3) -> 029 | Q145: =RIGHT(D145,3) -> 124 | R145: =PROPER(TRIM(J145)) -> Sneha | S145: =TRIM(PROPER(I145)) -> East | T145: =IFERROR(VLOOKUP(D145,Product_Reference!$A$1:$F$26,2,0),"Not Found!!") -> Tablet Keyboard | U145: =IFERROR(VLOOKUP(D145,Product_Reference!$A$1:$F$26,3,0),"Not Found!!") -> Accessories | V145: =IFERROR(VLOOKUP(D145,Product_Reference!$A$1:$F$26,4,0),"Not Found!!") -> KeyMaster | W145: =IFERROR(VLOOKUP(D145,Product_Reference!$A$1:$F$26,5,0),"Not Found!!") -> PQR Ltd | X145: =IFERROR(VLOOKUP(D145,Product_Reference!$A$1:$F$26,6,0),"Not Found!!") -> 3.8
A146: ORD1145 | B146: 46058 | C146: C036 | D146: P121 | E146: 1 | F146: 3200 | G146: 0.08 | H146: Card | I146: North | J146: Karan | K146: =PRODUCT(E146,F146) -> 3200 | L146: =PRODUCT(K146,G146) -> 256 | M146: =K146-L146 -> 2944 | N146: =IF(M146>=50000,"High Value",IF(M146>=20000,"Medium Value","Low Value")) -> Low Value | O146: =IF(AND(E146>=5,G146>=15%),"High",IF(OR(E146>=3,G146>=10%),"Medium","Low")) -> Low | P146: =RIGHT(C146,3) -> 036 | Q146: =RIGHT(D146,3) -> 21 | R146: =PROPER(TRIM(J146)) -> Karan | S146: =TRIM(PROPER(I146)) -> North | T146: =IFERROR(VLOOKUP(D146,Product_Reference!$A$1:$F$26,2,0),"Not Found!!") -> Not Found!! | U146: =IFERROR(VLOOKUP(D146,Product_Reference!$A$1:$F$26,3,0),"Not Found!!") -> Not Found!! | V146: =IFERROR(VLOOKUP(D146,Product_Reference!$A$1:$F$26,4,0),"Not Found!!") -> Not Found!! | W146: =IFERROR(VLOOKUP(D146,Product_Reference!$A$1:$F$26,5,0),"Not Found!!") -> Not Found!! | X146: =IFERROR(VLOOKUP(D146,Product_Reference!$A$1:$F$26,6,0),"Not Found!!") -> Not Found!!
A147: ORD1146 | B147: 46060 | C147: C006 | D147: P120 | E147: 6 | F147: 2200 | G147: 0.2 | H147: Card | I147: North | J147: Priya | K147: =PRODUCT(E147,F147) -> 13200 | L147: =PRODUCT(K147,G147) -> 2640 | M147: =K147-L147 -> 10560 | N147: =IF(M147>=50000,"High Value",IF(M147>=20000,"Medium Value","Low Value")) -> Low Value | O147: =IF(AND(E147>=5,G147>=15%),"High",IF(OR(E147>=3,G147>=10%),"Medium","Low")) -> High | P147: =RIGHT(C147,3) -> 006 | Q147: =RIGHT(D147,3) -> 120 | R147: =PROPER(TRIM(J147)) -> Priya | S147: =TRIM(PROPER(I147)) -> North | T147: =IFERROR(VLOOKUP(D147,Product_Reference!$A$1:$F$26,2,0),"Not Found!!") -> Desk Lamp | U147: =IFERROR(VLOOKUP(D147,Product_Reference!$A$1:$F$26,3,0),"Not Found!!") -> Furniture | V147: =IFERROR(VLOOKUP(D147,Product_Reference!$A$1:$F$26,4,0),"Not Found!!") -> BrightHome | W147: =IFERROR(VLOOKUP(D147,Product_Reference!$A$1:$F$26,5,0),"Not Found!!") -> XYZ Ltd | X147: =IFERROR(VLOOKUP(D147,Product_Reference!$A$1:$F$26,6,0),"Not Found!!") -> 3.9
A148: ORD1147 | B148: 46084 | C148: C018 | D148: P114 | E148: 6 | F148: 2500 | G148: 0.12 | H148: Card | I148: North | J148: Sneha | K148: =PRODUCT(E148,F148) -> 15000 | L148: =PRODUCT(K148,G148) -> 1800 | M148: =K148-L148 -> 13200 | N148: =IF(M148>=50000,"High Value",IF(M148>=20000,"Medium Value","Low Value")) -> Low Value | O148: =IF(AND(E148>=5,G148>=15%),"High",IF(OR(E148>=3,G148>=10%),"Medium","Low")) -> Medium | P148: =RIGHT(C148,3) -> 018 | Q148: =RIGHT(D148,3) -> 114 | R148: =PROPER(TRIM(J148)) -> Sneha | S148: =TRIM(PROPER(I148)) -> North | T148: =IFERROR(VLOOKUP(D148,Product_Reference!$A$1:$F$26,2,0),"Not Found!!") -> Power Bank 20000mAh | U148: =IFERROR(VLOOKUP(D148,Product_Reference!$A$1:$F$26,3,0),"Not Found!!") -> Accessories | V148: =IFERROR(VLOOKUP(D148,Product_Reference!$A$1:$F$26,4,0),"Not Found!!") -> PowerPlus | W148: =IFERROR(VLOOKUP(D148,Product_Reference!$A$1:$F$26,5,0),"Not Found!!") -> PQR Ltd | X148: =IFERROR(VLOOKUP(D148,Product_Reference!$A$1:$F$26,6,0),"Not Found!!") -> 4.1
... A151: ORD1150 | B151: 46068 | C151: C037 | D151: P111 | E151: 3 | F151: 18000 | G151: 0 | H151: Net Banking | I151: West | J151: Sneha | K151: =PRODUCT(E151,F151) -> 54000 | L151: =PRODUCT(K151,G151) -> 0 | M151: =K151-L151 -> 54000 | N151: =IF(M151>=50000,"High Value",IF(M151>=20000,"Medium Value","Low Value")) -> High Value | O151: =IF(AND(E151>=5,G151>=15%),"High",IF(OR(E151>=3,G151>=10%),"Medium","Low")) -> Medium | P151: =RIGHT(C151,3) -> 037 | Q151: =RIGHT(D151,3) -> 111 | R151: =PROPER(TRIM(J151)) -> Sneha | S151: =TRIM(PROPER(I151)) -> West | T151: =IFERROR(VLOOKUP(D151,Product_Reference!$A$1:$F$26,2,0),"Not Found!!") -> Gaming Monitor 24 | U151: =IFERROR(VLOOKUP(D151,Product_Reference!$A$1:$F$26,3,0),"Not Found!!") -> Electronics | V151: =IFERROR(VLOOKUP(D151,Product_Reference!$A$1:$F$26,4,0),"Not Found!!") -> ViewMax | W151: =IFERROR(VLOOKUP(D151,Product_Reference!$A$1:$F$26,5,0),"Not Found!!") -> XYZ Ltd | X151: =IFERROR(VLOOKUP(D151,Product_Reference!$A$1:$F$26,6,0),"Not Found!!") -> 4.2

Sheet Product_Reference
A1: Product_ID | B1: Product_Name | C1: Category | D1: Brand | E1: Supplier | F1: Product_Rating
A2: P101 | B2: Laptop Pro 14 | C2: Electronics | D2: TechPro | E2: ABC Ltd | F2: 4.5
A3: P102 | B3: Wireless Mouse | C3: Accessories | D3: ClickTech | E3: XYZ Ltd | F3: 4.2
A4: P103 | B4: Smartphone X | C4: Electronics | D4: MobileMax | E4: ABC Ltd | F4: 4.6
A5: P104 | B5: Tablet 10 | C5: Electronics | D5: TabWorld | E5: PQR Ltd | F5: 4.1
A6: P105 | B6: Mechanical Keyboard | C6: Accessories | D6: KeyMaster | E6: XYZ Ltd | F6: 4.4
A7: P106 | B7: Bluetooth Speaker | C7: Audio | D7: SoundMax | E7: LMN Ltd | F7: 3.9
A8: P107 | B8: USB-C Hub | C8: Accessories | D8: ConnectPro | E8: PQR Ltd | F8: 4.3
A9: P108 | B9: Smart Watch | C9: Wearables | D9: FitTech | E9: ABC Ltd | F9: 4
A10: P109 | B10: Noise Cancelling Headphones | C10: Audio | D10: SoundMax | E10: LMN Ltd | F10: 4.7
A11: P110 | B11: External SSD 1TB | C11: Storage | D11: DataDrive | E11: PQR Ltd | F11: 4.5
A12: P111 | B12: Gaming Monitor 24 | C12: Electronics | D12: ViewMax | E12: XYZ Ltd | F12: 4.2
A13: P112 | B13: Webcam HD | C13: Accessories | D13: VisionTech | E13: ABC Ltd | F13: 3.8
... A26: P125 | B26: Laser Printer | C26: Office Equipment | D26: PrintPro | E26: ABC Ltd | F26: 4.2
